{"Timestamp":"2021-03-28T12:58:40.915Z","Ack":"Success","Build":"E1157_CORE_APILW_19146596_R1","Version":"1157","Item":[{"ItemID":"312661692470","EndTime":"2021-04-18T08:20:58.000Z","ViewItemURLForNaturalSearch":"https://www.ebay.com/itm/72-216-Sq-Ft-Interlocking-EVA-Foam-Exercise-Floor-Mat-Flooring-Gym-Playground-/312661692470?var=","ListingType":"FixedPriceItem","Location":"Multiple Locations","PictureURL":["https://i.ebayimg.com/00/s/NTAwWDUwMA==/z/QZwAAOSw65pgCBFR/$_1.JPG?set_id=8800005007","https://i.ebayimg.com/00/s/NTAwWDUwMA==/z/yP4AAOSwjkhgCBFZ/$_1.JPG?set_id=8800005007","https://i.ebayimg.com/00/s/NTAwWDUwMA==/z/yyMAAOSw63pgCBFW/$_1.JPG?set_id=8800005007","https://i.ebayimg.com/00/s/NTAwWDUwMA==/z/9EkAAOSwGtFgCBFU/$_1.JPG?set_id=8800005007","https://i.ebayimg.com/00/s/NTAwWDUwMA==/z/6VkAAOSwGL1gCBFR/$_1.JPG?set_id=8800005007","https://i.ebayimg.com/00/s/NTAwWDUwMA==/z/ct8AAOSwnPBgCBFX/$_1.JPG?set_id=8800005007","https://i.ebayimg.com/00/s/NTAwWDUwMA==/z/xrgAAOSw1T9gCBFQ/$_1.JPG?set_id=8800005007","https://i.ebayimg.com/00/s/NTAwWDUwMA==/z/CaYAAOSwPcdgCBFS/$_1.JPG?set_id=8800005007"],"PrimaryCategoryID":"44079","PrimaryCategoryName":"Sporting Goods:Fitness, Running & Yoga:Fitness Equipment & Gear:Exercise Mats","BidCount":0,"ConvertedCurrentPrice":{"Value":51.99,"CurrencyID":"USD"},"ListingStatus":"Active","TimeLeft":"P20DT19H22M18S","Title":"72~ 216 Sq Ft Interlocking EVA Foam Exercise Floor Mat Flooring Gym Playground","HitCount":60805,"Country":"US","AutoPay":false,"Variations":{"Variation":[{"SKU":"US89013378","StartPrice":{"Value":139.99,"CurrencyID":"USD"},"Quantity":168,"VariationSpecifics":{"NameValueList":[{"Name":"Pack Quantity","Value":["54 Tiles(216sq)"]}]},"SellingStatus":{"QuantitySold":167,"QuantitySoldByPickupInStore":0}},{"SKU":"US89013534","StartPrice":{"Value":111.99,"CurrencyID":"USD"},"Quantity":565,"VariationSpecifics":{"NameValueList":[{"Name":"Pack Quantity","Value":["42 Tiles(168sq)"]}]},"SellingStatus":{"QuantitySold":271,"QuantitySoldByPickupInStore":0}},{"SKU":"USG89000510","StartPrice":{"Value":51.99,"CurrencyID":"USD"},"Quantity":271,"VariationSpecifics":{"NameValueList":[{"Name":"Pack Quantity","Value":["18 Tiles(72sq)"]}]},"SellingStatus":{"QuantitySold":163,"QuantitySoldByPickupInStore":0}},{"SKU":"USG89000511","StartPrice":{"Value":119.99,"CurrencyID":"USD"},"Quantity":16,"VariationSpecifics":{"NameValueList":[{"Name":"Pack Quantity","Value":["54 Tiles(216sq)-Multi Color"]}]},"SellingStatus":{"QuantitySold":16,"QuantitySoldByPickupInStore":0}}],"Pictures":[{"VariationSpecificName":"Pack Quantity","VariationSpecificPictureSet":[{"VariationSpecificValue":"18 Tiles(72sq)","PictureURL":["https://nbp-file.bytopo.com/Image/Ebay/190827/I19082701080/VPPicture_cdae37a3-6a3e-45f7-8665-212861a3c828.jpg"]},{"VariationSpecificValue":"42 Tiles(168sq)","PictureURL":["https://nbp-file.bytopo.com/Image/Ebay/190827/I19082701080/VPPicture_6bbe8519-83c5-4d56-9055-36c07526de8b.jpg"]},{"VariationSpecificValue":"54 Tiles(216sq)","PictureURL":["https://nbp-file.bytopo.com/Image/Ebay/190827/I19082701080/VPPicture_2a295fcb-5776-408c-8f28-3dfbc7332e86.jpg"]},{"VariationSpecificValue":"54 Tiles(216sq)-Multi Color","PictureURL":["https://nbp-file.bytopo.com/Image/Ebay/190827/I19082701080/VPPicture_9ab7b145-4a3d-4f5c-bd7e-458b892400d4.jpg"]}]}],"VariationSpecificsSet":{"NameValueList":[{"Name":"Pack Quantity","Value":["54 Tiles(216sq)","42 Tiles(168sq)","18 Tiles(72sq)","54 Tiles(216sq)-Multi Color"]}]}},"ConditionID":1000,"ConditionDisplayName":"New","QuantityAvailableHint":"MoreThan","QuantityThreshold":10},{"ItemID":"154317743968","EndTime":"2021-04-03T19:18:44.000Z","ViewItemURLForNaturalSearch":"https://www.ebay.com/itm/adidas-3-Stripes-Jogger-Pants-Mens-/154317743968?var=","ListingType":"FixedPriceItem","Location":"Spartanburg, South Carolina","PictureURL":["https://i.ebayimg.com/00/s/MTYwMFgxNjAw/z/QlgAAOSwpCxgWjhV/$_1.JPG?set_id=880000500F"],"PrimaryCategoryID":"59347","PrimaryCategoryName":"Sporting Goods:Fitness, Running & Yoga:Clothing & Accessories:Men's Clothing:Pants","BidCount":0,"ConvertedCurrentPrice":{"Value":21.99,"CurrencyID":"USD"},"ListingStatus":"Active","TimeLeft":"P6DT6H20M4S","Title":"adidas 3-Stripes Jogger Pants Men's","HitCount":21018,"Country":"US","AutoPay":true,"Variations":{"Variation":[{"SKU":"ED6924_210","StartPrice":{"Value":32,"CurrencyID":"USD"},"Quantity":0,"VariationSpecifics":{"NameValueList":[{"Name":"Color","Value":["Black / White"]},{"Name":"Size","Value":["XS"]}]},"SellingStatus":{"QuantitySold":0,"QuantitySoldByPickupInStore":0},"DiscountPriceInfo":{"OriginalRetailPrice":{"Value":45,"CurrencyID":"USD"},"PricingTreatment":"STP","SoldOneBay":false,"SoldOffeBay":false}},{"SKU":"ED6924_230","StartPrice":{"Value":32,"CurrencyID":"USD"},"Quantity":22,"VariationSpecifics":{"NameValueList":[{"Name":"Color","Value":["Black / White"]},{"Name":"Size","Value":["S"]}]},"SellingStatus":{"QuantitySold":22,"QuantitySoldByPickupInStore":0},"DiscountPriceInfo":{"OriginalRetailPrice":{"Value":45,"CurrencyID":"USD"},"PricingTreatment":"STP","SoldOneBay":false,"SoldOffeBay":false}},{"SKU":"ED6924_250","StartPrice":{"Value":32,"CurrencyID":"USD"},"Quantity":23,"VariationSpecifics":{"NameValueList":[{"Name":"Color","Value":["Black / White"]},{"Name":"Size","Value":["M"]}]},"SellingStatus":{"QuantitySold":23,"QuantitySoldByPickupInStore":0},"DiscountPriceInfo":{"OriginalRetailPrice":{"Value":45,"CurrencyID":"USD"},"PricingTreatment":"STP","SoldOneBay":false,"SoldOffeBay":false}},{"SKU":"ED6924_270","StartPrice":{"Value":32,"CurrencyID":"USD"},"Quantity":14,"VariationSpecifics":{"NameValueList":[{"Name":"Color","Value":["Black / White"]},{"Name":"Size","Value":["L"]}]},"SellingStatus":{"QuantitySold":14,"QuantitySoldByPickupInStore":0},"DiscountPriceInfo":{"OriginalRetailPrice":{"Value":45,"CurrencyID":"USD"},"PricingTreatment":"STP","SoldOneBay":false,"SoldOffeBay":false}},{"SKU":"ED6924_290","StartPrice":{"Value":32,"CurrencyID":"USD"},"Quantity":8,"VariationSpecifics":{"NameValueList":[{"Name":"Color","Value":["Black / White"]},{"Name":"Size","Value":["XL"]}]},"SellingStatus":{"QuantitySold":8,"QuantitySoldByPickupInStore":0},"DiscountPriceInfo":{"OriginalRetailPrice":{"Value":45,"CurrencyID":"USD"},"PricingTreatment":"STP","SoldOneBay":false,"SoldOffeBay":false}},{"SKU":"ED6924_310","StartPrice":{"Value":32,"CurrencyID":"USD"},"Quantity":0,"VariationSpecifics":{"NameValueList":[{"Name":"Color","Value":["Black / White"]},{"Name":"Size","Value":["2XL"]}]},"SellingStatus":{"QuantitySold":0,"QuantitySoldByPickupInStore":0},"DiscountPriceInfo":{"OriginalRetailPrice":{"Value":45,"CurrencyID":"USD"},"PricingTreatment":"STP","SoldOneBay":false,"SoldOffeBay":false}},{"SKU":"ED6924_320","StartPrice":{"Value":32,"CurrencyID":"USD"},"Quantity":0,"VariationSpecifics":{"NameValueList":[{"Name":"Color","Value":["Black / White"]},{"Name":"Size","Value":["3XL"]}]},"SellingStatus":{"QuantitySold":0,"QuantitySoldByPickupInStore":0},"DiscountPriceInfo":{"OriginalRetailPrice":{"Value":45,"CurrencyID":"USD"},"PricingTreatment":"STP","SoldOneBay":false,"SoldOffeBay":false}},{"SKU":"ED6924_330","StartPrice":{"Value":32,"CurrencyID":"USD"},"Quantity":0,"VariationSpecifics":{"NameValueList":[{"Name":"Color","Value":["Black / White"]},{"Name":"Size","Value":["4XL"]}]},"SellingStatus":{"QuantitySold":0,"QuantitySoldByPickupInStore":0},"DiscountPriceInfo":{"OriginalRetailPrice":{"Value":45,"CurrencyID":"USD"},"PricingTreatment":"STP","SoldOneBay":false,"SoldOffeBay":false}},{"SKU":"FL4844_210","StartPrice":{"Value":21.99,"CurrencyID":"USD"},"Quantity":0,"VariationSpecifics":{"NameValueList":[{"Name":"Color","Value":["Black / Carbon"]},{"Name":"Size","Value":["XS"]}]},"SellingStatus":{"QuantitySold":0,"QuantitySoldByPickupInStore":0},"DiscountPriceInfo":{"OriginalRetailPrice":{"Value":45,"CurrencyID":"USD"},"PricingTreatment":"STP","SoldOneBay":false,"SoldOffeBay":false}},{"SKU":"FL4844_230","StartPrice":{"Value":21.99,"CurrencyID":"USD"},"Quantity":136,"VariationSpecifics":{"NameValueList":[{"Name":"Color","Value":["Black / Carbon"]},{"Name":"Size","Value":["S"]}]},"SellingStatus":{"QuantitySold":97,"QuantitySoldByPickupInStore":0},"DiscountPriceInfo":{"OriginalRetailPrice":{"Value":45,"CurrencyID":"USD"},"PricingTreatment":"STP","SoldOneBay":false,"SoldOffeBay":false}},{"SKU":"FL4844_250","StartPrice":{"Value":21.99,"CurrencyID":"USD"},"Quantity":89,"VariationSpecifics":{"NameValueList":[{"Name":"Color","Value":["Black / Carbon"]},{"Name":"Size","Value":["M"]}]},"SellingStatus":{"QuantitySold":50,"QuantitySoldByPickupInStore":0},"DiscountPriceInfo":{"OriginalRetailPrice":{"Value":45,"CurrencyID":"USD"},"PricingTreatment":"STP","SoldOneBay":false,"SoldOffeBay":false}},{"SKU":"FL4844_270","StartPrice":{"Value":21.99,"CurrencyID":"USD"},"Quantity":143,"VariationSpecifics":{"NameValueList":[{"Name":"Color","Value":["Black / Carbon"]},{"Name":"Size","Value":["L"]}]},"SellingStatus":{"QuantitySold":104,"QuantitySoldByPickupInStore":0},"DiscountPriceInfo":{"OriginalRetailPrice":{"Value":45,"CurrencyID":"USD"},"PricingTreatment":"STP","SoldOneBay":false,"SoldOffeBay":false}},{"SKU":"FL4844_290","StartPrice":{"Value":21.99,"CurrencyID":"USD"},"Quantity":64,"VariationSpecifics":{"NameValueList":[{"Name":"Color","Value":["Black / Carbon"]},{"Name":"Size","Value":["XL"]}]},"SellingStatus":{"QuantitySold":25,"QuantitySoldByPickupInStore":0},"DiscountPriceInfo":{"OriginalRetailPrice":{"Value":45,"CurrencyID":"USD"},"PricingTreatment":"STP","SoldOneBay":false,"SoldOffeBay":false}},{"SKU":"FL4844_310","StartPrice":{"Value":21.99,"CurrencyID":"USD"},"Quantity":0,"VariationSpecifics":{"NameValueList":[{"Name":"Color","Value":["Black / Carbon"]},{"Name":"Size","Value":["2XL"]}]},"SellingStatus":{"QuantitySold":0,"QuantitySoldByPickupInStore":0},"DiscountPriceInfo":{"OriginalRetailPrice":{"Value":45,"CurrencyID":"USD"},"PricingTreatment":"STP","SoldOneBay":false,"SoldOffeBay":false}},{"SKU":"FL4844_320","StartPrice":{"Value":21.99,"CurrencyID":"USD"},"Quantity":0,"VariationSpecifics":{"NameValueList":[{"Name":"Color","Value":["Black / Carbon"]},{"Name":"Size","Value":["3XL"]}]},"SellingStatus":{"QuantitySold":0,"QuantitySoldByPickupInStore":0},"DiscountPriceInfo":{"OriginalRetailPrice":{"Value":45,"CurrencyID":"USD"},"PricingTreatment":"STP","SoldOneBay":false,"SoldOffeBay":false}},{"SKU":"FL4844_330","StartPrice":{"Value":21.99,"CurrencyID":"USD"},"Quantity":0,"VariationSpecifics":{"NameValueList":[{"Name":"Color","Value":["Black / Carbon"]},{"Name":"Size","Value":["4XL"]}]},"SellingStatus":{"QuantitySold":0,"QuantitySoldByPickupInStore":0},"DiscountPriceInfo":{"OriginalRetailPrice":{"Value":45,"CurrencyID":"USD"},"PricingTreatment":"STP","SoldOneBay":false,"SoldOffeBay":false}}],"Pictures":[{"VariationSpecificName":"Color","VariationSpecificPictureSet":[{"VariationSpecificValue":"Black / White","PictureURL":["https://assets.adidas.com/images/9705102acf0e44e4b6fdaa17017113f9_9366/ED6924_01_laydown.jpgED6924_01_laydown.jpg"]},{"VariationSpecificValue":"Black / Carbon","PictureURL":["https://assets.adidas.com/images/fa420a73277c4616a1d6aa1b011e99b4_9366/FL4844_01_laydown.jpgFL4844_01_laydown.jpg"]}]}],"VariationSpecificsSet":{"NameValueList":[{"Name":"Color","Value":["Black / White","Black / Carbon","Carbon / White"]},{"Name":"Size","Value":["XS","S","M","L","XL","2XL","3XL","4XL"]}]}},"ConditionID":1000,"ConditionDisplayName":"New with tags","QuantityAvailableHint":"MoreThan","QuantityThreshold":10,"DiscountPriceInfo":{"PricingTreatment":"STP"}},{"ItemID":"113827475151","EndTime":"2021-04-22T16:02:16.000Z","ViewItemURLForNaturalSearch":"https://www.ebay.com/itm/Nylon-Tricep-Rope-Pull-Press-Down-Push-Pull-Cord-Multi-Gym-Lat-Bar-Cable-Black-/113827475151?var=","ListingType":"FixedPriceItem","Location":"Lewisville, Texas","PictureURL":["https://i.ebayimg.com/00/s/MTYwMFgxNjAw/z/83QAAOSwKLVbY1h4/$_57.JPG?set_id=8800005007"],"PrimaryCategoryID":"179813","PrimaryCategoryName":"Sporting Goods:Fitness, Running & Yoga:Strength Training:Home Gym Attachments","BidCount":0,"ConvertedCurrentPrice":{"Value":17.91,"CurrencyID":"USD"},"ListingStatus":"Active","TimeLeft":"P25DT3H3M36S","Title":"Nylon Tricep Rope Pull Press Down Push Pull Cord Multi Gym Lat Bar Cable Black","HitCount":10306,"Country":"US","AutoPay":true,"Variations":{"Variation":[{"SKU":"Tricep Rope (Black)","StartPrice":{"Value":17.91,"CurrencyID":"USD"},"Quantity":500,"VariationSpecifics":{"NameValueList":[{"Name":"Selection","Value":["Tricep Rope"]}]},"SellingStatus":{"QuantitySold":73,"QuantitySoldByPickupInStore":0}}],"VariationSpecificsSet":{"NameValueList":[{"Name":"Selection","Value":["Tricep Rope"]}]}},"ConditionID":1000,"ConditionDisplayName":"New","QuantityAvailableHint":"MoreThan","QuantityThreshold":10},{"ItemID":"133697887222","EndTime":"2021-04-18T18:20:48.000Z","ViewItemURLForNaturalSearch":"https://www.ebay.com/itm/TRX-PRO-SUSPENSION-TRAINING-SYSTEM-9-Elite-Workout-Videos-/133697887222","ListingType":"FixedPriceItem","Location":"Toledo, Ohio","GalleryURL":"https://thumbs3.ebaystatic.com/pict/1336978872228080_1.jpg","PictureURL":["https://i.ebayimg.com/00/s/MTMxN1gxMTIy/z/9asAAOSwNjdf241z/$_12.JPG?set_id=880000500F","https://i.ebayimg.com/00/s/MTE0NVgxMDM5/z/FkAAAOSwSadf242F/$_12.JPG?set_id=880000500F","https://i.ebayimg.com/00/s/MTYwMFgxMjAw/z/dbIAAOSwcwlf240p/$_12.JPG?set_id=880000500F","https://i.ebayimg.com/00/s/MTYwMFgxMjAw/z/o~AAAOSwbdNf240s/$_12.JPG?set_id=880000500F","https://i.ebayimg.com/00/s/MTYwMFgxMjAw/z/u8QAAOSwW05f240v/$_12.JPG?set_id=880000500F","https://i.ebayimg.com/00/s/MTYwMFgxMjAw/z/Y9UAAOSwtCBf240y/$_12.JPG?set_id=880000500F","https://i.ebayimg.com/00/s/MTYwMFgxMjAw/z/gDUAAOSwpk9f240z/$_12.JPG?set_id=880000500F","https://i.ebayimg.com/00/s/NzkxWDU1MQ==/z/PpkAAOSwZ-5f2401/$_12.JPG?set_id=880000500F"],"PrimaryCategoryID":"79759","PrimaryCategoryName":"Sporting Goods:Fitness, Running & Yoga:Fitness Equipment & Gear:Resistance Trainers","BidCount":0,"ConvertedCurrentPrice":{"Value":129,"CurrencyID":"USD"},"ListingStatus":"Active","TimeLeft":"P21DT5H22M8S","Title":"TRX PRO SUSPENSION TRAINING SYSTEM With 9 Elite Workout Videos","HitCount":943,"Country":"US","AutoPay":true,"ConditionID":1000,"ConditionDisplayName":"New"},{"ItemID":"333436219200","EndTime":"2021-04-12T21:11:10.000Z","ViewItemURLForNaturalSearch":"https://www.ebay.com/itm/Nike-Dri-Fit-Head-Tie-Headband-3-0-/333436219200?var=","ListingType":"FixedPriceItem","Location":"Burnsville, Minnesota","PictureURL":["https://i.ebayimg.com/00/s/MTMzM1gxMDAw/z/OvMAAOSwY8td8qu6/$_57.JPG?set_id=8800005007"],"PrimaryCategoryID":"179811","PrimaryCategoryName":"Sporting Goods:Fitness, Running & Yoga:Clothing & Accessories:Sweatbands","BidCount":0,"ConvertedCurrentPrice":{"Value":9.79,"CurrencyID":"USD"},"ListingStatus":"Active","TimeLeft":"P15DT8H12M30S","Title":"Nike Dri-Fit Head Tie Headband 3.0","HitCount":41983,"Country":"US","AutoPay":false,"Variations":{"Variation":[{"SKU":"NTIEHB.01","StartPrice":{"Value":9.79,"CurrencyID":"USD"},"Quantity":169,"VariationSpecifics":{"NameValueList":[{"Name":"Color","Value":["White"]}]},"SellingStatus":{"QuantitySold":157,"QuantitySoldByPickupInStore":0},"ProductID":{"Value":"11036828171","Type":"Reference"}},{"SKU":"NTIEHB.23","StartPrice":{"Value":9.79,"CurrencyID":"USD"},"Quantity":101,"VariationSpecifics":{"NameValueList":[{"Name":"Color","Value":["Red"]}]},"SellingStatus":{"QuantitySold":95,"QuantitySoldByPickupInStore":0}},{"SKU":"NTIEHB.50","StartPrice":{"Value":9.79,"CurrencyID":"USD"},"Quantity":78,"VariationSpecifics":{"NameValueList":[{"Name":"Color","Value":["Navy"]}]},"SellingStatus":{"QuantitySold":68,"QuantitySoldByPickupInStore":0}},{"SKU":"NTIEHB.90","StartPrice":{"Value":9.79,"CurrencyID":"USD"},"Quantity":327,"VariationSpecifics":{"NameValueList":[{"Name":"Color","Value":["Black"]}]},"SellingStatus":{"QuantitySold":315,"QuantitySoldByPickupInStore":0},"ProductID":{"Value":"28035366638","Type":"Reference"}},{"SKU":"NTIEHB.11","StartPrice":{"Value":9.79,"CurrencyID":"USD"},"Quantity":75,"VariationSpecifics":{"NameValueList":[{"Name":"Color","Value":["Gray"]}]},"SellingStatus":{"QuantitySold":63,"QuantitySoldByPickupInStore":0}},{"SKU":"NTIEHB.43","StartPrice":{"Value":9.79,"CurrencyID":"USD"},"Quantity":106,"VariationSpecifics":{"NameValueList":[{"Name":"Color","Value":["Royal"]}]},"SellingStatus":{"QuantitySold":94,"QuantitySoldByPickupInStore":0}}],"Pictures":[{"VariationSpecificName":"Color","VariationSpecificPictureSet":[{"VariationSpecificValue":"White","PictureURL":["https://i.ebayimg.com/00/s/MTMzM1gxMDAw/z/iecAAOSwSq1d8qvh/$_57.JPG?set_id=8800005007"]},{"VariationSpecificValue":"Red","PictureURL":["https://i.ebayimg.com/00/s/MTMzM1gxMDAw/z/TNUAAOSwn~Jd8qvy/$_57.JPG?set_id=8800005007"]},{"VariationSpecificValue":"Navy","PictureURL":["https://i.ebayimg.com/00/s/MTMzM1gxMDAw/z/cwYAAOSwXAFd8qwc/$_57.JPG?set_id=8800005007"]},{"VariationSpecificValue":"Black","PictureURL":["https://i.ebayimg.com/00/s/MTMzM1gxMDAw/z/uQAAAOSwA3dd8qwq/$_57.JPG?set_id=8800005007"]},{"VariationSpecificValue":"Gray","PictureURL":["https://i.ebayimg.com/00/s/MTMzM1gxMDAw/z/l6YAAOSww~hd8qw3/$_57.JPG?set_id=8800005007"]},{"VariationSpecificValue":"Royal","PictureURL":["https://i.ebayimg.com/00/s/MTMzM1gxMDAw/z/V~AAAOSwQG9d8qxF/$_57.JPG?set_id=8800005007"]}]}],"VariationSpecificsSet":{"NameValueList":[{"Name":"Color","Value":["White","Red","Navy","Black","Gray","Royal"]}]}},"ConditionID":1000,"ConditionDisplayName":"New with tags","GlobalShipping":true},{"ItemID":"254896499489","EndTime":"2021-04-09T19:16:34.000Z","ViewItemURLForNaturalSearch":"https://www.ebay.com/itm/Women-Men-Gym-Gloves-Wrist-Wrap-Workout-Weight-Lifting-Fitness-Exercise-US-/254896499489?var=","ListingType":"FixedPriceItem","Location":"Harlingen, Texas","PictureURL":["https://i.ebayimg.com/00/s/MTMyN1gxNDg4/z/HRIAAOSwUhJgR8Gd/$_57.JPG?set_id=8800005007","https://i.ebayimg.com/00/s/MTEzNVgxMDg3/z/nEcAAOSwH4VgR8G4/$_57.JPG?set_id=8800005007","https://i.ebayimg.com/00/s/MTA5NFgxMTU0/z/PygAAOSwPKNgR8G-/$_57.JPG?set_id=8800005007","https://i.ebayimg.com/00/s/MTQ1N1gxNjAw/z/3hIAAOSwy8BgR8HG/$_57.JPG?set_id=8800005007","https://i.ebayimg.com/00/s/MTA3NFgxMDA5/z/5-QAAOSwvClgR8HM/$_57.JPG?set_id=8800005007","https://i.ebayimg.com/00/s/MTE4M1gxMTg3/z/BSgAAOSw~llgR8HU/$_57.JPG?set_id=8800005007","https://i.ebayimg.com/00/s/MTIxOFgxMjc5/z/jkkAAOSw9axgR8H6/$_57.JPG?set_id=8800005007","https://i.ebayimg.com/00/s/OTMxWDk1Nw==/z/Js0AAOSwOEZgR8IF/$_57.JPG?set_id=8800005007","https://i.ebayimg.com/00/s/MTYwMFgxNDk3/z/WgIAAOSwSvlgR8IW/$_57.JPG?set_id=8800005007","https://i.ebayimg.com/00/s/MTYwMFgxNTA3/z/PpUAAOSwDYJgR8If/$_57.JPG?set_id=8800005007","https://i.ebayimg.com/00/s/MTYwMFgxMzk4/z/ubkAAOSw79JgR8I3/$_57.JPG?set_id=8800005007","https://i.ebayimg.com/00/s/MTA4NlgxMDY4/z/EMUAAOSw6LRgR8OG/$_57.JPG?set_id=8800005007"],"PrimaryCategoryID":"185070","PrimaryCategoryName":"Sporting Goods:Fitness, Running & Yoga:Strength Training:Gloves, Straps & Hooks","BidCount":0,"ConvertedCurrentPrice":{"Value":14.95,"CurrencyID":"USD"},"ListingStatus":"Active","TimeLeft":"P12DT6H17M54S","Title":"Women/Men Gym Gloves With Wrist Wrap Workout Weight Lifting Fitness Exercise US","HitCount":2220,"Country":"US","AutoPay":true,"Variations":{"Variation":[{"StartPrice":{"Value":14.95,"CurrencyID":"USD"},"Quantity":21,"VariationSpecifics":{"NameValueList":[{"Name":"Size","Value":["Medium"]}]},"SellingStatus":{"QuantitySold":12,"QuantitySoldByPickupInStore":0}},{"StartPrice":{"Value":14.95,"CurrencyID":"USD"},"Quantity":53,"VariationSpecifics":{"NameValueList":[{"Name":"Size","Value":["Large"]}]},"SellingStatus":{"QuantitySold":45,"QuantitySoldByPickupInStore":0}},{"StartPrice":{"Value":14.95,"CurrencyID":"USD"},"Quantity":20,"VariationSpecifics":{"NameValueList":[{"Name":"Size","Value":["Small"]}]},"SellingStatus":{"QuantitySold":10,"QuantitySoldByPickupInStore":0}},{"StartPrice":{"Value":14.95,"CurrencyID":"USD"},"Quantity":29,"VariationSpecifics":{"NameValueList":[{"Name":"Size","Value":["X-Large"]}]},"SellingStatus":{"QuantitySold":19,"QuantitySoldByPickupInStore":0}}],"VariationSpecificsSet":{"NameValueList":[{"Name":"Size","Value":["Small","Medium","Large","X-Large"]}]}},"ConditionID":1000,"ConditionDisplayName":"New","QuantityAvailableHint":"MoreThan","QuantityThreshold":10,"GlobalShipping":true},{"ItemID":"284113557258","EndTime":"2021-04-13T12:58:08.000Z","ViewItemURLForNaturalSearch":"https://www.ebay.com/itm/Bench-Press-Barbell-Rack-Adjustable-Weight-Folding-Squat-Fitness-Gym-Training-/284113557258","ListingType":"FixedPriceItem","Location":"California","GalleryURL":"https://thumbs3.ebaystatic.com/pict/2841135572588080_1.jpg","PictureURL":["https://i.ebayimg.com/00/s/MTAwMVgxMDAx/z/UKwAAOSwunJf1g~e/$_12.JPG?set_id=880000500F","https://i.ebayimg.com/00/s/MTAwMVgxMDAx/z/J~YAAOSwjQRf1g~e/$_12.JPG?set_id=880000500F","https://i.ebayimg.com/00/s/MTAwMVgxMDAx/z/iFYAAOSwz7Jf1g~e/$_12.JPG?set_id=880000500F","https://i.ebayimg.com/00/s/MTAwMVgxMDAx/z/2P0AAOSwCQ1f1g~f/$_12.JPG?set_id=880000500F","https://i.ebayimg.com/00/s/MTAwMVgxMDAx/z/xqYAAOSw7P9f1g~e/$_12.JPG?set_id=880000500F","https://i.ebayimg.com/00/s/MTAwMVgxMDAx/z/PnMAAOSw~MFf1g~e/$_12.JPG?set_id=880000500F","https://i.ebayimg.com/00/s/MTAwMVgxMDAx/z/-f8AAOSw0GJf1g~f/$_12.JPG?set_id=880000500F","https://i.ebayimg.com/00/s/MTAwMVgxMDAx/z/m4IAAOSwEvhf1g~e/$_12.JPG?set_id=880000500F","https://i.ebayimg.com/00/s/MTAwMVgxMDAx/z/y3wAAOSwaPFf1g~e/$_12.JPG?set_id=880000500F"],"PrimaryCategoryID":"15281","PrimaryCategoryName":"Sporting Goods:Fitness, Running & Yoga:Strength Training:Benches","BidCount":0,"ConvertedCurrentPrice":{"Value":99.99,"CurrencyID":"USD"},"ListingStatus":"Active","TimeLeft":"P15DT23H59M28S","Title":"Bench Press Barbell Rack Adjustable Weight Folding Squat Fitness Gym Training","HitCount":24390,"Country":"US","AutoPay":true,"ConditionID":1000,"ConditionDisplayName":"New","QuantityAvailableHint":"MoreThan","QuantityThreshold":10},{"ItemID":"283997548622","EndTime":"2021-04-02T08:36:35.000Z","ViewItemURLForNaturalSearch":"https://www.ebay.com/itm/Jump-Rope-Digital-Counting-Calorie-Counter-Fitness-Alarm-Reminder-/283997548622","ListingType":"FixedPriceItem","Location":"Houston, Texas","GalleryURL":"https://thumbs3.ebaystatic.com/pict/2839975486228080_1.jpg","PictureURL":["https://i.ebayimg.com/00/s/OTM5WDExMTg=/z/Pd4AAOSwZM9fT1mI/$_12.JPG?set_id=880000500F","https://i.ebayimg.com/00/s/MTEwMFgxMTAw/z/pvoAAOSw7kRfT1mK/$_12.JPG?set_id=880000500F","https://i.ebayimg.com/00/s/MTAyOVgxMTAw/z/JsIAAOSwcm5fT1mM/$_12.JPG?set_id=880000500F","https://i.ebayimg.com/00/s/MTAzOFgxMDI0/z/4XgAAOSwTwxfT1mN/$_12.JPG?set_id=880000500F","https://i.ebayimg.com/00/s/MTEwMFgxMDU4/z/-DMAAOSwt55fT1mP/$_12.JPG?set_id=880000500F","https://i.ebayimg.com/00/s/MTEwMFgxMTAw/z/vroAAOSw-zdfT1mQ/$_12.JPG?set_id=880000500F","https://i.ebayimg.com/00/s/OTY0WDkxNQ==/z/ijIAAOSw7xlfT1mS/$_12.JPG?set_id=880000500F"],"PrimaryCategoryID":"62134","PrimaryCategoryName":"Sporting Goods:Fitness, Running & Yoga:Fitness Equipment & Gear:Jump Ropes","BidCount":0,"ConvertedCurrentPrice":{"Value":10.99,"CurrencyID":"USD"},"ListingStatus":"Active","TimeLeft":"P4DT19H37M55S","Title":"Jump Rope Digital Counting With Calorie Counter For Fitness, With Alarm Reminder","HitCount":8531,"Country":"US","AutoPay":false,"ConditionID":1000,"ConditionDisplayName":"New","QuantityAvailableHint":"MoreThan","QuantityThreshold":10},{"ItemID":"384039237238","EndTime":"2021-04-18T17:16:06.000Z","ViewItemURLForNaturalSearch":"https://www.ebay.com/itm/2021-Touch-Smart-Watch-Women-Men-Heart-Rate-iPhone-Android-IOS-Waterproof-/384039237238?var=","ListingType":"FixedPriceItem","Location":"Abingdon, Maryland","PictureURL":["https://i.ebayimg.com/00/s/MTAxMFgxMDEw/z/~~4AAOSw7YRgUy8F/$_57.JPG","https://i.ebayimg.com/00/s/NzIyWDc5MA==/z/p~EAAOSwhfVc~c~K/$_12.JPG?set_id=880000500F","https://i.ebayimg.com/00/s/MTAxMFgxMDEw/z/ctQAAOSwOFdc5MVk/$_12.JPG?set_id=880000500F","https://i.ebayimg.com/00/s/MTAxMFgxMDEw/z/PFcAAOSwJAdc0AGc/$_12.JPG?set_id=880000500F","https://i.ebayimg.com/00/s/MTAxMFgxMDEw/z/37YAAOSwASRcz~wY/$_12.JPG?set_id=880000500F","https://i.ebayimg.com/00/s/MTAxMFgxMDEw/z/~bwAAOSwLFVcz~wb/$_12.JPG?set_id=880000500F","https://i.ebayimg.com/00/s/MTAxMFgxMDEw/z/fkMAAOSwHghcz~wc/$_12.JPG?set_id=880000500F","https://i.ebayimg.com/00/s/MTAxMFgxMDEw/z/l90AAOSwkClcz~wd/$_12.JPG?set_id=880000500F","https://i.ebayimg.com/00/s/MTAxMFgxMDEw/z/wpoAAOSwz55cz~wg/$_12.JPG?set_id=880000500F","https://i.ebayimg.com/00/s/MTAxMFgxMDEw/z/sXwAAOSwLdpcz~wh/$_12.JPG?set_id=880000500F","https://i.ebayimg.com/00/s/MTAxMFgxMDEw/z/hXIAAOSwvSNcz~wi/$_12.JPG?set_id=880000500F","https://i.ebayimg.com/00/s/MTAxMFgxMDEw/z/hfYAAOSw6jJcz~wj/$_12.JPG?set_id=880000500F"],"PrimaryCategoryID":"178893","PrimaryCategoryName":"Cell Phones & Accessories:Smart Watches","BidCount":0,"ConvertedCurrentPrice":{"Value":11.99,"CurrencyID":"USD"},"ListingStatus":"Active","TimeLeft":"P21DT4H17M26S","Title":"2021 Touch Smart Watch Women Men Heart Rate For iPhone Android IOS Waterproof","HitCount":2879,"Country":"US","AutoPay":true,"Variations":{"Variation":[{"SKU":"ID116-BK","StartPrice":{"Value":12.99,"CurrencyID":"USD"},"Quantity":49,"VariationSpecifics":{"NameValueList":[{"Name":"Color","Value":["Black"]}]},"SellingStatus":{"QuantitySold":46,"QuantitySoldByPickupInStore":0}},{"SKU":"ID116-PU","StartPrice":{"Value":12.99,"CurrencyID":"USD"},"Quantity":11,"VariationSpecifics":{"NameValueList":[{"Name":"Color","Value":["Purple"]}]},"SellingStatus":{"QuantitySold":8,"QuantitySoldByPickupInStore":0}},{"SKU":"ID116-GR","StartPrice":{"Value":12.99,"CurrencyID":"USD"},"Quantity":9,"VariationSpecifics":{"NameValueList":[{"Name":"Color","Value":["Green"]}]},"SellingStatus":{"QuantitySold":6,"QuantitySoldByPickupInStore":0}},{"SKU":"ID116-RD","StartPrice":{"Value":12.99,"CurrencyID":"USD"},"Quantity":11,"VariationSpecifics":{"NameValueList":[{"Name":"Color","Value":["Red"]}]},"SellingStatus":{"QuantitySold":8,"QuantitySoldByPickupInStore":0}},{"SKU":"ID116-BU","StartPrice":{"Value":12.99,"CurrencyID":"USD"},"Quantity":17,"VariationSpecifics":{"NameValueList":[{"Name":"Color","Value":["Blue"]}]},"SellingStatus":{"QuantitySold":14,"QuantitySoldByPickupInStore":0}},{"SKU":"M3-BK","StartPrice":{"Value":11.99,"CurrencyID":"USD"},"Quantity":6,"VariationSpecifics":{"NameValueList":[{"Name":"Color","Value":["M3 black"]}]},"SellingStatus":{"QuantitySold":3,"QuantitySoldByPickupInStore":0}}],"Pictures":[{"VariationSpecificName":"Color","VariationSpecificPictureSet":[{"VariationSpecificValue":"Black","PictureURL":["https://i.ebayimg.com/00/s/ODAwWDgwMA==/z/86EAAOSw7Ytf2iGa/$_10.JPG?set_id=880000500F"]},{"VariationSpecificValue":"Purple","PictureURL":["https://i.ebayimg.com/00/s/NjAwWDYwMA==/z/HJkAAOSwDtxdUTiZ/$_12.JPG?set_id=880000500F"]},{"VariationSpecificValue":"Green","PictureURL":["https://i.ebayimg.com/00/s/ODAwWDgwMA==/z/keQAAOSwNjdf2iGd/$_10.JPG?set_id=880000500F"]},{"VariationSpecificValue":"Red","PictureURL":["https://i.ebayimg.com/00/s/ODAwWDgwMA==/z/Y-8AAOSwGb9f2iGh/$_10.JPG?set_id=880000500F"]},{"VariationSpecificValue":"Blue","PictureURL":["https://i.ebayimg.com/00/s/ODAwWDgwMA==/z/PwEAAOSwvJ9f2iGc/$_10.JPG?set_id=880000500F"]},{"VariationSpecificValue":"M3 black","PictureURL":["https://i.ebayimg.com/images/g/0-IAAOSwo~lc6KSj/s-l1600.jpg"]}]}],"VariationSpecificsSet":{"NameValueList":[{"Name":"Color","Value":["Black","Purple","Green","Red","Blue","M3 black"]}]}},"ConditionID":1000,"ConditionDisplayName":"New","QuantityAvailableHint":"MoreThan","QuantityThreshold":10},{"ItemID":"164643939807","EndTime":"2021-04-14T10:52:44.000Z","ViewItemURLForNaturalSearch":"https://www.ebay.com/itm/MaxiClimber-Vertical-Maxi-Climber-Workout-Fitness-Machine-w-Diet-Manual-Sealed-/164643939807","ListingType":"FixedPriceItem","Location":"Dearborn Heights, Michigan","GalleryURL":"https://thumbs4.ebaystatic.com/pict/1646439398078080_1.jpg","PictureURL":["https://i.ebayimg.com/00/s/MTUwNFgxMDIw/z/m58AAOSwi9RgACD7/$_57.PNG?set_id=8800005007","https://i.ebayimg.com/00/s/MTYwMFg5MjY=/z/RMwAAOSwOqFgACEV/$_57.PNG?set_id=8800005007","https://i.ebayimg.com/00/s/MTYwMFg5OTQ=/z/RAMAAOSwI-hf~TCh/$_57.PNG?set_id=8800005007","https://i.ebayimg.com/00/s/MTYwMFg1OTg=/z/F5sAAOSwapxf~TCI/$_57.PNG?set_id=8800005007","https://i.ebayimg.com/00/s/MTYwMFgxMDcw/z/9pkAAOSwfjRgACE1/$_57.PNG?set_id=8800005007"],"PrimaryCategoryID":"28062","PrimaryCategoryName":"Sporting Goods:Fitness, Running & Yoga:Cardio Equipment:Stair Machines & Steppers","BidCount":0,"ConvertedCurrentPrice":{"Value":139,"CurrencyID":"USD"},"ListingStatus":"Active","TimeLeft":"P16DT21H54M4S","Title":"MaxiClimber Vertical Maxi Climber Workout Fitness Machine w Diet Manual Sealed","HitCount":6643,"Country":"US","AutoPay":true,"ConditionID":1000,"ConditionDisplayName":"New","QuantityAvailableHint":"MoreThan","QuantityThreshold":10},{"ItemID":"142799412337","EndTime":"2021-04-18T09:26:36.000Z","ViewItemURLForNaturalSearch":"https://www.ebay.com/itm/Lat-Pull-Down-Machine-Multifunction-Low-Row-Bar-Cable-Fitness-Body-Workout-Gym-/142799412337","ListingType":"FixedPriceItem","Location":"Phoenix, Arizona","GalleryURL":"https://thumbs2.ebaystatic.com/pict/1427994123378080_7.jpg","PictureURL":["https://i.ebayimg.com/00/s/MTUwMFg5NTU=/z/t8AAAOSw8DZfZH~S/$_57.JPG?set_id=8800005007","https://i.ebayimg.com/00/s/MTUwMFgxMjI5/z/FUwAAOSwrgVfZH~X/$_57.JPG?set_id=8800005007","https://i.ebayimg.com/00/s/MTUwMFgxMTE2/z/3YIAAOSwTSdfZH~g/$_57.JPG?set_id=8800005007","https://i.ebayimg.com/00/s/MTMwM1gxNTAw/z/k3AAAOSwYNpeaDX6/$_57.JPG?set_id=8800005007","https://i.ebayimg.com/00/s/MTQxNlgxNTAw/z/ZYIAAOSwpB5eaDYJ/$_57.JPG?set_id=8800005007","https://i.ebayimg.com/00/s/MTM5OVgxNTAw/z/yxYAAOSwx5pfZH~l/$_57.JPG?set_id=8800005007"],"PrimaryCategoryID":"158923","PrimaryCategoryName":"Sporting Goods:Fitness, Running & Yoga:Strength Training:Home Gyms","BidCount":0,"ConvertedCurrentPrice":{"Value":249.99,"CurrencyID":"USD"},"ListingStatus":"Active","TimeLeft":"P20DT20H27M56S","Title":"Lat Pull Down Machine Multifunction Low Row Bar Cable Fitness Body Workout Gym","HitCount":69540,"Country":"US","AutoPay":true,"ConditionID":1000,"ConditionDisplayName":"New","QuantityAvailableHint":"MoreThan","QuantityThreshold":10},{"ItemID":"293619882638","EndTime":"2021-04-19T20:04:19.000Z","ViewItemURLForNaturalSearch":"https://www.ebay.com/itm/Garmin-Forerunner-235-Frost-Blue-Garmin-Manufacturer-Refurbished-/293619882638","ListingType":"FixedPriceItem","Location":"Levittown, Pennsylvania","GalleryURL":"https://thumbs3.ebaystatic.com/pict/2936198826388080_1.jpg","PictureURL":["https://i.ebayimg.com/00/s/MTUwMFgxMDc3/z/5wYAAOSwFjZe7Ro2/$_57.JPG?set_id=8800005007","https://i.ebayimg.com/00/s/MTEyMFgxMTIw/z/t8EAAOSwqmxgWNaH/$_57.JPG?set_id=8800005007"],"PrimaryCategoryID":"75230","PrimaryCategoryName":"Sporting Goods:Fitness, Running & Yoga:Fitness Technology:GPS & Running Watches","BidCount":0,"ConvertedCurrentPrice":{"Value":109,"CurrencyID":"USD"},"ListingStatus":"Active","TimeLeft":"P22DT7H5M39S","Title":"Garmin Forerunner 235 - Frost Blue (Garmin Manufacturer Refurbished)","HitCount":128175,"Country":"US","AutoPay":true,"ConditionID":2500,"ConditionDisplayName":"Seller refurbished","QuantityAvailableHint":"MoreThan","QuantityThreshold":10,"GlobalShipping":true,"ConditionDescription":"This Garmin Manufacturer Refurbished product is tested and guaranteed to look and work like new. The refurbishing process includes functionality testing, basic cleaning, inspection, and repackaging. The product ships with all relevant accessories, a minimum 365 day warranty, and may arrive in a generic box."},{"ItemID":"353343922664","EndTime":"2021-04-06T12:57:29.000Z","ViewItemURLForNaturalSearch":"https://www.ebay.com/itm/MRX-Weight-Lifting-Belt-Training-Gym-Fitness-Bodybuilding-Back-Support-Workout-/353343922664?var=","ListingType":"FixedPriceItem","Location":"Schenectady, New York","PictureURL":["https://i.ebayimg.com/00/s/MTYwMFgxNjAw/z/JNsAAOSwc6VgAZDO/$_57.JPG?set_id=8800005007","https://i.ebayimg.com/00/s/MTAwMFgxMDAw/z/SwgAAOSwxXNf9bI6/$_57.JPG?set_id=8800005007","https://i.ebayimg.com/00/s/MTYwMFgxNjAw/z/X6EAAOSwL0Nf9bIA/$_57.JPG?set_id=8800005007"],"PrimaryCategoryID":"36155","PrimaryCategoryName":"Sporting Goods:Fitness, Running & Yoga:Strength Training:Belts","BidCount":0,"ConvertedCurrentPrice":{"Value":12.99,"CurrencyID":"USD"},"ListingStatus":"Active","TimeLeft":"P8DT23H58M49S","Title":"MRX Weight Lifting Belt Training Gym Fitness Bodybuilding Back Support Workout","HitCount":9666,"Country":"US","AutoPay":true,"Variations":{"Variation":[{"SKU":"N-2010-BR-S","StartPrice":{"Value":12.99,"CurrencyID":"USD"},"Quantity":86,"VariationSpecifics":{"NameValueList":[{"Name":"Color","Value":["Black/Red"]},{"Name":"Size","Value":["Small"]}]},"SellingStatus":{"QuantitySold":26,"QuantitySoldByPickupInStore":0}},{"SKU":"N-2010-BR-M","StartPrice":{"Value":12.99,"CurrencyID":"USD"},"Quantity":85,"VariationSpecifics":{"NameValueList":[{"Name":"Color","Value":["Black/Red"]},{"Name":"Size","Value":["Medium"]}]},"SellingStatus":{"QuantitySold":49,"QuantitySoldByPickupInStore":0}},{"SKU":"N-2010-BR-L","StartPrice":{"Value":12.99,"CurrencyID":"USD"},"Quantity":43,"VariationSpecifics":{"NameValueList":[{"Name":"Color","Value":["Black/Red"]},{"Name":"Size","Value":["Large"]}]},"SellingStatus":{"QuantitySold":32,"QuantitySoldByPickupInStore":0}},{"SKU":"N-2010-BR-XL","StartPrice":{"Value":12.99,"CurrencyID":"USD"},"Quantity":75,"VariationSpecifics":{"NameValueList":[{"Name":"Color","Value":["Black/Red"]},{"Name":"Size","Value":["X-Large"]}]},"SellingStatus":{"QuantitySold":15,"QuantitySoldByPickupInStore":0}},{"SKU":"N-2010-BR-2XL","StartPrice":{"Value":12.99,"CurrencyID":"USD"},"Quantity":71,"VariationSpecifics":{"NameValueList":[{"Name":"Color","Value":["Black/Red"]},{"Name":"Size","Value":["2XL-Large"]}]},"SellingStatus":{"QuantitySold":11,"QuantitySoldByPickupInStore":0}},{"SKU":"N-2010-BB-S","StartPrice":{"Value":12.99,"CurrencyID":"USD"},"Quantity":24,"VariationSpecifics":{"NameValueList":[{"Name":"Color","Value":["Black/Blue"]},{"Name":"Size","Value":["Small"]}]},"SellingStatus":{"QuantitySold":8,"QuantitySoldByPickupInStore":0}},{"SKU":"N-2010-BB-M","StartPrice":{"Value":12.99,"CurrencyID":"USD"},"Quantity":47,"VariationSpecifics":{"NameValueList":[{"Name":"Color","Value":["Black/Blue"]},{"Name":"Size","Value":["Medium"]}]},"SellingStatus":{"QuantitySold":32,"QuantitySoldByPickupInStore":0}},{"SKU":"N-2010-BB-L","StartPrice":{"Value":12.99,"CurrencyID":"USD"},"Quantity":49,"VariationSpecifics":{"NameValueList":[{"Name":"Color","Value":["Black/Blue"]},{"Name":"Size","Value":["Large"]}]},"SellingStatus":{"QuantitySold":22,"QuantitySoldByPickupInStore":0}},{"SKU":"N-2010-BB-XL","StartPrice":{"Value":12.99,"CurrencyID":"USD"},"Quantity":50,"VariationSpecifics":{"NameValueList":[{"Name":"Color","Value":["Black/Blue"]},{"Name":"Size","Value":["X-Large"]}]},"SellingStatus":{"QuantitySold":7,"QuantitySoldByPickupInStore":0}},{"SKU":"N-2010-BB-2XL","StartPrice":{"Value":12.99,"CurrencyID":"USD"},"Quantity":25,"VariationSpecifics":{"NameValueList":[{"Name":"Color","Value":["Black/Blue"]},{"Name":"Size","Value":["2XL-Large"]}]},"SellingStatus":{"QuantitySold":7,"QuantitySoldByPickupInStore":0}},{"SKU":"N-2010-BG-S","StartPrice":{"Value":12.99,"CurrencyID":"USD"},"Quantity":23,"VariationSpecifics":{"NameValueList":[{"Name":"Color","Value":["Black/Green"]},{"Name":"Size","Value":["Small"]}]},"SellingStatus":{"QuantitySold":9,"QuantitySoldByPickupInStore":0}},{"SKU":"N-2010-BG-M","StartPrice":{"Value":12.99,"CurrencyID":"USD"},"Quantity":48,"VariationSpecifics":{"NameValueList":[{"Name":"Color","Value":["Black/Green"]},{"Name":"Size","Value":["Medium"]}]},"SellingStatus":{"QuantitySold":19,"QuantitySoldByPickupInStore":0}},{"SKU":"N-2010-BG-L","StartPrice":{"Value":12.99,"CurrencyID":"USD"},"Quantity":48,"VariationSpecifics":{"NameValueList":[{"Name":"Color","Value":["Black/Green"]},{"Name":"Size","Value":["Large"]}]},"SellingStatus":{"QuantitySold":7,"QuantitySoldByPickupInStore":0}},{"SKU":"N-2010-BG-XL","StartPrice":{"Value":12.99,"CurrencyID":"USD"},"Quantity":49,"VariationSpecifics":{"NameValueList":[{"Name":"Color","Value":["Black/Green"]},{"Name":"Size","Value":["X-Large"]}]},"SellingStatus":{"QuantitySold":6,"QuantitySoldByPickupInStore":0}},{"SKU":"N-2010-BG-2XL","StartPrice":{"Value":12.99,"CurrencyID":"USD"},"Quantity":25,"VariationSpecifics":{"NameValueList":[{"Name":"Color","Value":["Black/Green"]},{"Name":"Size","Value":["2XL-Large"]}]},"SellingStatus":{"QuantitySold":7,"QuantitySoldByPickupInStore":0}}],"Pictures":[{"VariationSpecificName":"Color","VariationSpecificPictureSet":[{"VariationSpecificValue":"Black/Red","PictureURL":["https://i.ebayimg.com/00/s/MTUwMFgxNTAw/z/fKEAAOSwGB1f9bIH/$_57.JPG?set_id=8800005007","https://i.ebayimg.com/00/s/MTA5MFgxNjAw/z/KRwAAOSw~wdf9bIe/$_57.JPG?set_id=8800005007","https://i.ebayimg.com/00/s/MTUwMFgxNTAw/z/FTwAAOSwEvZf9bIR/$_57.JPG?set_id=8800005007","https://i.ebayimg.com/00/s/MTUwMFgxNTAw/z/5KYAAOSwVqJf9bIY/$_57.JPG?set_id=8800005007","https://i.ebayimg.com/00/s/MTUwMFgxNTAw/z/tv4AAOSwocxf9bIo/$_57.JPG?set_id=8800005007"]},{"VariationSpecificValue":"Black/Blue","PictureURL":["https://i.ebayimg.com/00/s/MTAwMFgxMDAw/z/rIwAAOSwGbhf9bIu/$_57.JPG?set_id=8800005007","https://i.ebayimg.com/00/s/MTA5MFgxNjAw/z/HZYAAOSwRYNf9bJF/$_57.JPG?set_id=8800005007","https://i.ebayimg.com/00/s/MTUwMFgxNTAw/z/1ZwAAOSw1tRf9bI3/$_57.JPG?set_id=8800005007","https://i.ebayimg.com/00/s/MTUwMFgxNTAw/z/L9sAAOSwFJpf9bI-/$_57.JPG?set_id=8800005007","https://i.ebayimg.com/00/s/MTUwMFgxNTAw/z/DV4AAOSwUllf9bJP/$_57.JPG?set_id=8800005007"]},{"VariationSpecificValue":"Black/Green","PictureURL":["https://i.ebayimg.com/00/s/MTUwMFgxNTAw/z/fwQAAOSwbRhf9bJY/$_57.JPG?set_id=8800005007","https://i.ebayimg.com/00/s/MTA5MFgxNjAw/z/InsAAOSwURtf9bJv/$_57.JPG?set_id=8800005007","https://i.ebayimg.com/00/s/MTUwMFgxNTAw/z/KqUAAOSwuMxf9bJh/$_57.JPG?set_id=8800005007","https://i.ebayimg.com/00/s/MTUwMFgxNTAw/z/ab0AAOSwp5Bf9bJo/$_57.JPG?set_id=8800005007","https://i.ebayimg.com/00/s/MTUwMFgxNTAw/z/GMgAAOSwSaJf9bJ4/$_57.JPG?set_id=8800005007"]}]}],"VariationSpecificsSet":{"NameValueList":[{"Name":"Color","Value":["Black/Red","Black/Blue","Black/Green"]},{"Name":"Size","Value":["Small","Medium","Large","X-Large","2XL-Large"]}]}},"ConditionID":1000,"ConditionDisplayName":"New","QuantityAvailableHint":"MoreThan","QuantityThreshold":10,"GlobalShipping":true},{"ItemID":"174217258779","EndTime":"2021-04-11T19:01:59.000Z","ViewItemURLForNaturalSearch":"https://www.ebay.com/itm/Reebok-Mens-Active-Enhanced-Backpack-Large-/174217258779?var=","ListingType":"FixedPriceItem","Location":"Spartanburg, South Carolina","PictureURL":["https://i.ebayimg.com/00/s/MTYwMFgxNjAw/z/~KgAAOSwSF1f9p2-/$_1.JPG?set_id=880000500F","https://i.ebayimg.com/00/s/ODQwWDg0MA==/z/cNUAAOSwo99f9p27/$_1.JPG?set_id=880000500F","https://i.ebayimg.com/00/s/ODQwWDg0MA==/z/MS0AAOSw1~5f9p27/$_1.JPG?set_id=880000500F","https://i.ebayimg.com/00/s/ODQwWDg0MA==/z/NboAAOSwij1f9p27/$_1.JPG?set_id=880000500F"],"PrimaryCategoryID":"68816","PrimaryCategoryName":"Sporting Goods:Fitness, Running & Yoga:Gym Bags","BidCount":0,"ConvertedCurrentPrice":{"Value":19.99,"CurrencyID":"USD"},"ListingStatus":"Active","TimeLeft":"P14DT6H3M19S","Title":"Reebok Men's Active Enhanced Backpack Large","HitCount":7543,"Country":"US","AutoPay":true,"Variations":{"Variation":[{"SKU":"FR5562_500","StartPrice":{"Value":19.99,"CurrencyID":"USD"},"Quantity":133,"VariationSpecifics":{"NameValueList":[{"Name":"Color","Value":["Black"]},{"Name":"Size","Value":["N SZ"]}]},"SellingStatus":{"QuantitySold":74,"QuantitySoldByPickupInStore":0},"DiscountPriceInfo":{"OriginalRetailPrice":{"Value":50,"CurrencyID":"USD"},"PricingTreatment":"STP","SoldOneBay":false,"SoldOffeBay":false}},{"SKU":"FR5564_500","StartPrice":{"Value":39.97,"CurrencyID":"USD"},"Quantity":8,"VariationSpecifics":{"NameValueList":[{"Name":"Color","Value":["Legacy Red"]},{"Name":"Size","Value":["N SZ"]}]},"SellingStatus":{"QuantitySold":8,"QuantitySoldByPickupInStore":0},"DiscountPriceInfo":{"OriginalRetailPrice":{"Value":50,"CurrencyID":"USD"},"PricingTreatment":"STP","SoldOneBay":false,"SoldOffeBay":false}},{"SKU":"GH0176_500","StartPrice":{"Value":44.97,"CurrencyID":"USD"},"Quantity":59,"VariationSpecifics":{"NameValueList":[{"Name":"Color","Value":["Poplar Green"]},{"Name":"Size","Value":["N SZ"]}]},"SellingStatus":{"QuantitySold":0,"QuantitySoldByPickupInStore":0},"DiscountPriceInfo":{"OriginalRetailPrice":{"Value":50,"CurrencyID":"USD"},"PricingTreatment":"STP","SoldOneBay":false,"SoldOffeBay":false}}],"Pictures":[{"VariationSpecificName":"Color","VariationSpecificPictureSet":[{"VariationSpecificValue":"Black","PictureURL":["https://assets.reebok.com/images/c70b8afffbe44f6f94d6aae700100051_9366/FR5562_01_standard.jpgFR5562_01_standard.jpg","https://assets.reebok.com/images/w_840,h_840,f_auto,q_auto:sensitive,fl_lossy/26ba299ee2f3408c9addaae7000d5d71_9366/FR5562_02_standard_hover.jpg","https://assets.reebok.com/images/w_840,h_840,f_auto,q_auto:sensitive,fl_lossy/d4c24d92cb514ff5987caae700105305_9366/FR5562_03_standard.jpg","https://assets.reebok.com/images/w_840,h_840,f_auto,q_auto:sensitive,fl_lossy/8536b536692d4736bff1aaf100bd82ad_9366/FR5562_04_standard.jpg"]},{"VariationSpecificValue":"Legacy Red","PictureURL":["https://assets.reebok.com/images/d733e18ceb2e4d30a8d1aae700163b2f_9366/FR5564_01_standard.jpgFR5564_01_standard.jpg","https://assets.reebok.com/images/w_840,h_840,f_auto,q_auto:sensitive,fl_lossy/6d16464e84534e50b3e0aae7000b8bda_9366/FR5564_02_standard_hover.jpg","https://assets.reebok.com/images/w_840,h_840,f_auto,q_auto:sensitive,fl_lossy/28007a24fb904fa991d3aae70015c80c_9366/FR5564_03_standard.jpg","https://assets.reebok.com/images/w_840,h_840,f_auto,q_auto:sensitive,fl_lossy/276541a46b1a4d89beaeaaf10184be9d_9366/FR5564_04_standard.jpg"]},{"VariationSpecificValue":"Poplar Green","PictureURL":["https://assets.reebok.com/images/b201f9ccc3a94670a985abc300e6e25b_9366/GH0176_01_standard.jpgGH0176_01_standard.jpg","https://assets.reebok.com/images/w_840,h_840,f_auto,q_auto:sensitive,fl_lossy/8337669dd0d549c693cdabc300e6ef16_9366/GH0176_02_standard_hover.jpg","https://assets.reebok.com/images/w_840,h_840,f_auto,q_auto:sensitive,fl_lossy/02041aa91f784149a379abc300e6fef7_9366/GH0176_03_standard.jpg","https://assets.reebok.com/images/w_840,h_840,f_auto,q_auto:sensitive,fl_lossy/232dcc876fca4acbbbf4abc300e6c6d5_9366/GH0176_04_standard.jpg"]}]}],"VariationSpecificsSet":{"NameValueList":[{"Name":"Color","Value":["Black","Legacy Red","Poplar Green"]},{"Name":"Size","Value":["N SZ"]}]}},"ConditionID":1000,"ConditionDisplayName":"New with tags","QuantityAvailableHint":"Limited","DiscountPriceInfo":{"PricingTreatment":"STP"}},{"ItemID":"154336072975","EndTime":"2021-04-18T13:17:02.000Z","ViewItemURLForNaturalSearch":"https://www.ebay.com/itm/adidas-Own-Run-Hooded-Wind-Jacket-Mens-/154336072975?var=","ListingType":"FixedPriceItem","Location":"Spartanburg, South Carolina","PictureURL":["https://i.ebayimg.com/00/s/MTYwMFgxNjAw/z/5CoAAOSwU7hgX2IL/$_1.JPG?set_id=880000500F","https://i.ebayimg.com/00/s/ODQwWDg0MA==/z/QZAAAOSwhFdgX2IK/$_1.JPG?set_id=880000500F","https://i.ebayimg.com/00/s/ODQwWDg0MA==/z/DuMAAOSwdS9gX2IK/$_1.JPG?set_id=880000500F","https://i.ebayimg.com/00/s/ODQwWDg0MA==/z/NgEAAOSwjptgX2IK/$_1.JPG?set_id=880000500F","https://i.ebayimg.com/00/s/ODQwWDg0MA==/z/H54AAOSwzW1gX2IK/$_1.JPG?set_id=880000500F","https://i.ebayimg.com/00/s/ODQwWDg0MA==/z/YFQAAOSwhaNgX2IK/$_1.JPG?set_id=880000500F","https://i.ebayimg.com/00/s/ODQwWDg0MA==/z/kT8AAOSwmutgX2IK/$_1.JPG?set_id=880000500F","https://i.ebayimg.com/00/s/ODQwWDg0MA==/z/V3MAAOSwzlpgX2IK/$_1.JPG?set_id=880000500F"],"PrimaryCategoryID":"185702","PrimaryCategoryName":"Clothing, Shoes & Accessories:Men:Men's Clothing:Activewear:Activewear Jackets","BidCount":0,"ConvertedCurrentPrice":{"Value":27.99,"CurrencyID":"USD"},"ListingStatus":"Active","TimeLeft":"P21DT18M22S","Title":"adidas Own the Run Hooded Wind Jacket Men's","HitCount":47454,"Country":"US","AutoPay":true,"Variations":{"Variation":[{"SKU":"FL6964_210","StartPrice":{"Value":27.99,"CurrencyID":"USD"},"Quantity":0,"VariationSpecifics":{"NameValueList":[{"Name":"Color","Value":["Black"]},{"Name":"Size","Value":["XS"]}]},"SellingStatus":{"QuantitySold":0,"QuantitySoldByPickupInStore":0},"DiscountPriceInfo":{"OriginalRetailPrice":{"Value":58,"CurrencyID":"USD"},"PricingTreatment":"STP","SoldOneBay":false,"SoldOffeBay":false}},{"SKU":"FL6964_230","StartPrice":{"Value":27.99,"CurrencyID":"USD"},"Quantity":186,"VariationSpecifics":{"NameValueList":[{"Name":"Color","Value":["Black"]},{"Name":"Size","Value":["S"]}]},"SellingStatus":{"QuantitySold":147,"QuantitySoldByPickupInStore":0},"DiscountPriceInfo":{"OriginalRetailPrice":{"Value":58,"CurrencyID":"USD"},"PricingTreatment":"STP","SoldOneBay":false,"SoldOffeBay":false}},{"SKU":"FL6964_250","StartPrice":{"Value":27.99,"CurrencyID":"USD"},"Quantity":361,"VariationSpecifics":{"NameValueList":[{"Name":"Color","Value":["Black"]},{"Name":"Size","Value":["M"]}]},"SellingStatus":{"QuantitySold":322,"QuantitySoldByPickupInStore":0},"DiscountPriceInfo":{"OriginalRetailPrice":{"Value":58,"CurrencyID":"USD"},"PricingTreatment":"STP","SoldOneBay":false,"SoldOffeBay":false}},{"SKU":"FL6964_270","StartPrice":{"Value":27.99,"CurrencyID":"USD"},"Quantity":258,"VariationSpecifics":{"NameValueList":[{"Name":"Color","Value":["Black"]},{"Name":"Size","Value":["L"]}]},"SellingStatus":{"QuantitySold":258,"QuantitySoldByPickupInStore":0},"DiscountPriceInfo":{"OriginalRetailPrice":{"Value":58,"CurrencyID":"USD"},"PricingTreatment":"STP","SoldOneBay":false,"SoldOffeBay":false}},{"SKU":"FL6964_290","StartPrice":{"Value":27.99,"CurrencyID":"USD"},"Quantity":95,"VariationSpecifics":{"NameValueList":[{"Name":"Color","Value":["Black"]},{"Name":"Size","Value":["XL"]}]},"SellingStatus":{"QuantitySold":95,"QuantitySoldByPickupInStore":0},"DiscountPriceInfo":{"OriginalRetailPrice":{"Value":58,"CurrencyID":"USD"},"PricingTreatment":"STP","SoldOneBay":false,"SoldOffeBay":false}},{"SKU":"FL6964_310","StartPrice":{"Value":27.99,"CurrencyID":"USD"},"Quantity":11,"VariationSpecifics":{"NameValueList":[{"Name":"Color","Value":["Black"]},{"Name":"Size","Value":["2XL"]}]},"SellingStatus":{"QuantitySold":11,"QuantitySoldByPickupInStore":0},"DiscountPriceInfo":{"OriginalRetailPrice":{"Value":58,"CurrencyID":"USD"},"PricingTreatment":"STP","SoldOneBay":false,"SoldOffeBay":false}}],"Pictures":[{"VariationSpecificName":"Color","VariationSpecificPictureSet":[{"VariationSpecificValue":"Black","PictureURL":["https://assets.adidas.com/images/e12fb022322746a9b2fbaab101487414_9366/FL6964_000_plp_model.jpgFL6964_000_plp_model.jpg","https://assets.adidas.com/images/w_840,h_840,f_auto,q_auto:sensitive,fl_lossy/4daba23bc7644b84b2a6aab1014cee86_9366/FL6964_21_model.jpg","https://assets.adidas.com/images/w_840,h_840,f_auto,q_auto:sensitive,fl_lossy/9130b6b76dba4e35b5dfaab1014c8efe_9366/FL6964_22_model.jpg","https://assets.adidas.com/images/w_840,h_840,f_auto,q_auto:sensitive,fl_lossy/1b75cf9c4fe745a2887faab1014ecece_9366/FL6964_23_hover_model.jpg","https://assets.adidas.com/images/w_840,h_840,f_auto,q_auto:sensitive,fl_lossy/a46cf38fb3eb455a8482aab1014f2a34_9366/FL6964_25_model.jpg","https://assets.adidas.com/images/w_840,h_840,f_auto,q_auto:sensitive,fl_lossy/14fa2ee4f0f541a1b526aab1014a66bb_9366/FL6964_41_detail.jpg","https://assets.adidas.com/images/w_840,h_840,f_auto,q_auto:sensitive,fl_lossy/811ce98df6734f8db4f0aab1014ba990_9366/FL6964_42_detail.jpg","https://assets.adidas.com/images/w_840,h_840,f_auto,q_auto:sensitive,fl_lossy/38d6ab21f1614835952caab1014b15f2_9366/FL6964_43_detail.jpg"]}]}],"VariationSpecificsSet":{"NameValueList":[{"Name":"Color","Value":["Black"]},{"Name":"Size","Value":["XS","S","M","L","XL","2XL"]}]}},"ConditionID":1000,"ConditionDisplayName":"New with tags","QuantityAvailableHint":"Limited","DiscountPriceInfo":{"PricingTreatment":"STP"}},{"ItemID":"383716892504","EndTime":"2021-04-12T07:01:41.000Z","ViewItemURLForNaturalSearch":"https://www.ebay.com/itm/Hand-Grip-Strength-Power-Trainer-Gripper-Strengthener-Adjustable-Gym-Exerciser-/383716892504","ListingType":"FixedPriceItem","Location":"Pleasant Hill, California","GalleryURL":"https://thumbs1.ebaystatic.com/pict/3837168925048080_1.jpg","PictureURL":["https://i.ebayimg.com/00/s/MTAwMFgxMDAw/z/oTkAAOSwNHpfXHJG/$_57.PNG?set_id=8800005007","https://i.ebayimg.com/00/s/MTAwMFgxMDAw/z/ZbYAAOSwXS5fXHJH/$_57.JPG?set_id=8800005007","https://i.ebayimg.com/00/s/MTAwMFgxMDAw/z/OfsAAOSw9opfXHJG/$_57.JPG?set_id=8800005007","https://i.ebayimg.com/00/s/NTAwWDUwMA==/z/QHUAAOSw8WJfXHJH/$_57.JPG?set_id=8800005007"],"PrimaryCategoryID":"137862","PrimaryCategoryName":"Sporting Goods:Fitness, Running & Yoga:Fitness Equipment & Gear:Hand Grippers","BidCount":0,"ConvertedCurrentPrice":{"Value":7.99,"CurrencyID":"USD"},"ListingStatus":"Active","TimeLeft":"P14DT18H3M1S","Title":"Hand Grip Strength Power Trainer Gripper Strengthener Adjustable Gym Exerciser ","HitCount":25816,"Country":"US","AutoPay":true,"ConditionID":1000,"ConditionDisplayName":"New","QuantityAvailableHint":"MoreThan","QuantityThreshold":10,"GlobalShipping":true},{"ItemID":"114587353748","EndTime":"2021-04-21T13:30:56.000Z","ViewItemURLForNaturalSearch":"https://www.ebay.com/itm/Shema97-SEC-Coaches-wearing-BLK-LRG-W-LANYARD-/114587353748?var=","ListingType":"FixedPriceItem","Location":"Clermont, Florida","PictureURL":["https://i.ebayimg.com/00/s/NTI1WDc4Ng==/z/97cAAOSwGqFft1JS/$_57.JPG?set_id=8800005007","https://i.ebayimg.com/00/s/ODQwWDEyNjA=/z/wQYAAOSwpMpf99n8/$_57.JPG?set_id=8800005007","https://i.ebayimg.com/00/s/MTU4NlgxNTg2/z/TLQAAOSwHpZft0~m/$_57.JPG?set_id=8800005007","https://i.ebayimg.com/00/s/MTEyNVgxMTI1/z/YD8AAOSwzq5f2C2q/$_57.JPG?set_id=8800005007","https://i.ebayimg.com/00/s/NDQ2WDUxMg==/z/pdcAAOSwB1Nft02c/$_57.JPG?set_id=8800005007","https://i.ebayimg.com/00/s/NDk1WDg4MA==/z/wVkAAOSwpLJf99tY/$_57.JPG?set_id=8800005007","https://i.ebayimg.com/00/s/NjYwWDgzOA==/z/o0QAAOSwL8hf99vS/$_57.JPG?set_id=8800005007","https://i.ebayimg.com/00/s/NDg4WDYwNg==/z/naQAAOSwdtxfwomb/$_57.JPG?set_id=8800005007","https://i.ebayimg.com/00/s/MTIzNFgxMzgz/z/lHYAAOSwv7Zft1GH/$_57.JPG?set_id=8800005007","https://i.ebayimg.com/00/s/OTAwWDE2MDA=/z/BikAAOSwcL1f99ne/$_57.JPG?set_id=8800005007","https://i.ebayimg.com/00/s/NzEyWDc0Mw==/z/-xUAAOSwEJdfwmJ6/$_57.JPG?set_id=8800005007","https://i.ebayimg.com/00/s/NDk1WDg4MA==/z/R7UAAOSw1uZf99pD/$_57.JPG?set_id=8800005007"],"PrimaryCategoryID":"116724","PrimaryCategoryName":"Clothing, Shoes & Accessories:Specialty:Costumes, Reenactment, Theater:Accessories:Masks & Eye Masks","BidCount":0,"ConvertedCurrentPrice":{"Value":19.95,"CurrencyID":"USD"},"ListingStatus":"Active","TimeLeft":"P24DT32M16S","Title":"Shema97-SEC Coaches wearing-BLK LRG W/ LANYARD!","HitCount":22900,"Country":"US","AutoPay":true,"Variations":{"Variation":[{"SKU":"129702","StartPrice":{"Value":19.95,"CurrencyID":"USD"},"Quantity":60,"VariationSpecifics":{"NameValueList":[{"Name":"Color","Value":["Black"]},{"Name":"Size","Value":["S"]}]},"SellingStatus":{"QuantitySold":47,"QuantitySoldByPickupInStore":0}},{"SKU":"129701","StartPrice":{"Value":19.95,"CurrencyID":"USD"},"Quantity":14,"VariationSpecifics":{"NameValueList":[{"Name":"Color","Value":["White"]},{"Name":"Size","Value":["S"]}]},"SellingStatus":{"QuantitySold":14,"QuantitySoldByPickupInStore":0}},{"SKU":"239702","StartPrice":{"Value":23.95,"CurrencyID":"USD"},"Quantity":565,"VariationSpecifics":{"NameValueList":[{"Name":"Color","Value":["Black"]},{"Name":"Size","Value":["L"]}]},"SellingStatus":{"QuantitySold":547,"QuantitySoldByPickupInStore":0}},{"SKU":"239701","StartPrice":{"Value":22.95,"CurrencyID":"USD"},"Quantity":49,"VariationSpecifics":{"NameValueList":[{"Name":"Color","Value":["White"]},{"Name":"Size","Value":["L"]}]},"SellingStatus":{"QuantitySold":33,"QuantitySoldByPickupInStore":0}}],"VariationSpecificsSet":{"NameValueList":[{"Name":"Size","Value":["S","L"]},{"Name":"Color","Value":["Black","White"]}]}},"ConditionID":1000,"ConditionDisplayName":"New with tags","QuantityAvailableHint":"MoreThan","QuantityThreshold":10,"GlobalShipping":true},{"ItemID":"272287227395","EndTime":"2021-04-26T18:11:43.000Z","ViewItemURLForNaturalSearch":"https://www.ebay.com/itm/Heavy-Duty-2Fit-Sweat-Suit-Sauna-Exercise-Gym-Suit-Fitness-Weight-Loss-Anti-Rip-/272287227395?var=","ListingType":"FixedPriceItem","Location":"Orlando, Florida","PictureURL":["https://i.ebayimg.com/00/s/MTUwMFgxMjkw/z/0lEAAOSwNuxXbuhx/$_57.JPG?set_id=8800005007","https://i.ebayimg.com/00/s/MTUwMFgxNTAw/z/7iYAAOSw3YNXbuh~/$_57.JPG?set_id=8800005007","https://i.ebayimg.com/00/s/NzAwWDEwMDA=/z/T5MAAOSwmudZ8wI0/$_57.JPG?set_id=8800005007","https://i.ebayimg.com/00/s/MTYwMFgxNjAw/z/~a8AAOSw-kdXxT8N/$_57.JPG?set_id=8800005007","https://i.ebayimg.com/00/s/MTYwMFgxNjAw/z/s3cAAOSwFV9XxT8T/$_57.JPG?set_id=8800005007"],"PrimaryCategoryID":"179812","PrimaryCategoryName":"Sporting Goods:Fitness, Running & Yoga:Clothing & Accessories:Sauna Suits","BidCount":0,"ConvertedCurrentPrice":{"Value":29.99,"CurrencyID":"USD"},"ListingStatus":"Active","TimeLeft":"P29DT5H13M3S","Title":"Heavy Duty 2Fit Sweat Suit Sauna Exercise Gym Suit Fitness Weight Loss Anti Rip","HitCount":117703,"Country":"US","AutoPay":false,"Variations":{"Variation":[{"SKU":"2FIT HOODIE SUIT - L","StartPrice":{"Value":29.99,"CurrencyID":"USD"},"Quantity":673,"VariationSpecifics":{"NameValueList":[{"Name":"size","Value":["Large"]}]},"SellingStatus":{"QuantitySold":611,"QuantitySoldByPickupInStore":0}},{"SKU":"2FIT HOODIE SUIT - XL","StartPrice":{"Value":29.99,"CurrencyID":"USD"},"Quantity":884,"VariationSpecifics":{"NameValueList":[{"Name":"size","Value":["XL"]}]},"SellingStatus":{"QuantitySold":825,"QuantitySoldByPickupInStore":0}},{"SKU":"2FIT HOODIE SUIT - 2XL","StartPrice":{"Value":29.99,"CurrencyID":"USD"},"Quantity":861,"VariationSpecifics":{"NameValueList":[{"Name":"size","Value":["2XL"]}]},"SellingStatus":{"QuantitySold":817,"QuantitySoldByPickupInStore":0}},{"SKU":"2FIT HOODIE SUIT - 3XL","StartPrice":{"Value":29.99,"CurrencyID":"USD"},"Quantity":712,"VariationSpecifics":{"NameValueList":[{"Name":"size","Value":["3XL"]}]},"SellingStatus":{"QuantitySold":657,"QuantitySoldByPickupInStore":0}},{"SKU":"2FIT HOODIE SUIT - 4XL","StartPrice":{"Value":29.99,"CurrencyID":"USD"},"Quantity":581,"VariationSpecifics":{"NameValueList":[{"Name":"size","Value":["4XL"]}]},"SellingStatus":{"QuantitySold":509,"QuantitySoldByPickupInStore":0}},{"SKU":"2FIT HOODIE SUIT - 5XL","StartPrice":{"Value":29.99,"CurrencyID":"USD"},"Quantity":484,"VariationSpecifics":{"NameValueList":[{"Name":"size","Value":["5XL"]}]},"SellingStatus":{"QuantitySold":409,"QuantitySoldByPickupInStore":0}},{"SKU":"2FIT HOODIE SUIT - 6XL","StartPrice":{"Value":29.99,"CurrencyID":"USD"},"Quantity":565,"VariationSpecifics":{"NameValueList":[{"Name":"size","Value":["6XL"]}]},"SellingStatus":{"QuantitySold":484,"QuantitySoldByPickupInStore":0}},{"SKU":"2FIT HOODIE SUIT - S","StartPrice":{"Value":29.99,"CurrencyID":"USD"},"Quantity":247,"VariationSpecifics":{"NameValueList":[{"Name":"size","Value":["small"]}]},"SellingStatus":{"QuantitySold":157,"QuantitySoldByPickupInStore":0}},{"SKU":"2FIT HOODIE SUIT - M","StartPrice":{"Value":29.99,"CurrencyID":"USD"},"Quantity":480,"VariationSpecifics":{"NameValueList":[{"Name":"size","Value":["Medium"]}]},"SellingStatus":{"QuantitySold":401,"QuantitySoldByPickupInStore":0}},{"SKU":"2FIT HOODIE SUIT - 7XL","StartPrice":{"Value":29.99,"CurrencyID":"USD"},"Quantity":237,"VariationSpecifics":{"NameValueList":[{"Name":"size","Value":["7XL"]}]},"SellingStatus":{"QuantitySold":151,"QuantitySoldByPickupInStore":0}},{"SKU":"2FIT HOODIE SUIT - 8XL","StartPrice":{"Value":29.99,"CurrencyID":"USD"},"Quantity":265,"VariationSpecifics":{"NameValueList":[{"Name":"size","Value":["8XL"]}]},"SellingStatus":{"QuantitySold":186,"QuantitySoldByPickupInStore":0}},{"SKU":"2FIT HOODIE SUIT - XS","StartPrice":{"Value":29.99,"CurrencyID":"USD"},"Quantity":119,"VariationSpecifics":{"NameValueList":[{"Name":"size","Value":["XS"]}]},"SellingStatus":{"QuantitySold":20,"QuantitySoldByPickupInStore":0}},{"SKU":"2FIT HOODIE SUIT - 9XL","StartPrice":{"Value":29.99,"CurrencyID":"USD"},"Quantity":100,"VariationSpecifics":{"NameValueList":[{"Name":"size","Value":["9XL"]}]},"SellingStatus":{"QuantitySold":3,"QuantitySoldByPickupInStore":0}}],"VariationSpecificsSet":{"NameValueList":[{"Name":"size","Value":["XS","small","Medium","Large","XL","2XL","3XL","4XL","5XL","6XL","7XL","8XL","9XL"]}]}},"ConditionID":1000,"ConditionDisplayName":"New with tags","QuantityAvailableHint":"MoreThan","QuantityThreshold":10},{"ItemID":"294006809855","EndTime":"2021-04-10T14:04:51.000Z","ViewItemURLForNaturalSearch":"https://www.ebay.com/itm/NEW-5-45LB-VINYL-DIPPED-KETTLE-BELL-GYM-WEIGHT-100-IRON-5-10-15-20-25-30-35-40-/294006809855?var=","ListingType":"FixedPriceItem","Location":"Birmingham, Michigan","PictureURL":["https://i.ebayimg.com/00/s/MTA2MVg5NzM=/z/93gAAOSwlEhgI-Q-/$_1.JPG?set_id=880000500F","https://i.ebayimg.com/00/s/MTA2MVgxMDYx/z/UHEAAOSwzHdgI-S2/$_1.JPG?set_id=880000500F","https://i.ebayimg.com/00/s/MTEyNFgxMDkz/z/Ty0AAOSwIe1gI-Sp/$_1.JPG?set_id=880000500F","https://i.ebayimg.com/00/s/MTMwMFgxMTgx/z/OqUAAOSwBIxgI-Sf/$_1.JPG?set_id=880000500F","https://i.ebayimg.com/00/s/MTA5M1g5NDg=/z/CAkAAOSws2dgI-SU/$_1.JPG?set_id=880000500F","https://i.ebayimg.com/00/s/MTE5M1gxMDkz/z/JWIAAOSws4dgI-SJ/$_1.JPG?set_id=880000500F","https://i.ebayimg.com/00/s/MTE4N1gxMDE3/z/Ts4AAOSwIe1gI-R-/$_1.JPG?set_id=880000500F"],"PrimaryCategoryID":"179814","PrimaryCategoryName":"Sporting Goods:Fitness, Running & Yoga:Strength Training:Kettlebells","BidCount":0,"ConvertedCurrentPrice":{"Value":19.99,"CurrencyID":"USD"},"ListingStatus":"Active","TimeLeft":"P13DT1H6M11S","Title":"NEW 5-45LB VINYL DIPPED KETTLE BELL GYM WEIGHT 100% IRON! 5,10,15,20,25,30,35,40","HitCount":9397,"Country":"US","AutoPay":false,"Variations":{"Variation":[{"SKU":"5LB KB_5L","StartPrice":{"Value":19.99,"CurrencyID":"USD"},"Quantity":15,"VariationSpecifics":{"NameValueList":[{"Name":"Weight","Value":["5LB"]}]},"SellingStatus":{"QuantitySold":6,"QuantitySoldByPickupInStore":0}},{"SKU":"10LB KB_10","StartPrice":{"Value":24.99,"CurrencyID":"USD"},"Quantity":20,"VariationSpecifics":{"NameValueList":[{"Name":"Weight","Value":["10LB"]}]},"SellingStatus":{"QuantitySold":12,"QuantitySoldByPickupInStore":0}},{"SKU":"15LB KB_15","StartPrice":{"Value":29.99,"CurrencyID":"USD"},"Quantity":27,"VariationSpecifics":{"NameValueList":[{"Name":"Weight","Value":["15LB"]}]},"SellingStatus":{"QuantitySold":21,"QuantitySoldByPickupInStore":0}},{"SKU":"20LB KB_20","StartPrice":{"Value":42.99,"CurrencyID":"USD"},"Quantity":32,"VariationSpecifics":{"NameValueList":[{"Name":"Weight","Value":["20LB"]}]},"SellingStatus":{"QuantitySold":24,"QuantitySoldByPickupInStore":0}},{"SKU":"25LB KB_25","StartPrice":{"Value":48.99,"CurrencyID":"USD"},"Quantity":28,"VariationSpecifics":{"NameValueList":[{"Name":"Weight","Value":["25LB"]}]},"SellingStatus":{"QuantitySold":20,"QuantitySoldByPickupInStore":0}},{"SKU":"30LB KB_30","StartPrice":{"Value":59.99,"CurrencyID":"USD"},"Quantity":20,"VariationSpecifics":{"NameValueList":[{"Name":"Weight","Value":["30LB"]}]},"SellingStatus":{"QuantitySold":14,"QuantitySoldByPickupInStore":0}},{"SKU":"35LB KB_35","StartPrice":{"Value":69.99,"CurrencyID":"USD"},"Quantity":14,"VariationSpecifics":{"NameValueList":[{"Name":"Weight","Value":["35LB"]}]},"SellingStatus":{"QuantitySold":8,"QuantitySoldByPickupInStore":0}},{"SKU":"40LB KB_40","StartPrice":{"Value":79.99,"CurrencyID":"USD"},"Quantity":13,"VariationSpecifics":{"NameValueList":[{"Name":"Weight","Value":["40LB"]}]},"SellingStatus":{"QuantitySold":4,"QuantitySoldByPickupInStore":0}},{"SKU":"45LB KB_45","StartPrice":{"Value":89.99,"CurrencyID":"USD"},"Quantity":11,"VariationSpecifics":{"NameValueList":[{"Name":"Weight","Value":["45LB"]}]},"SellingStatus":{"QuantitySold":2,"QuantitySoldByPickupInStore":0}}],"VariationSpecificsSet":{"NameValueList":[{"Name":"Weight","Value":["5LB","10LB","15LB","20LB","25LB","30LB","35LB","40LB","45LB"]}]}},"ConditionID":1000,"ConditionDisplayName":"New","QuantityAvailableHint":"MoreThan","QuantityThreshold":10,"GlobalShipping":true},{"ItemID":"193667634449","EndTime":"2021-04-17T10:00:55.000Z","ViewItemURLForNaturalSearch":"https://www.ebay.com/itm/Folding-Electric-Power-Treadmill-Motorized-Walking-Fitness-Machine-Running-Home-/193667634449","ListingType":"FixedPriceItem","Location":"Rowland Heights, California","GalleryURL":"https://thumbs2.ebaystatic.com/pict/1936676344498080_1.jpg","PictureURL":["https://i.ebayimg.com/00/s/MTAwMVgxMDAx/z/euEAAOSwIe5fYzN5/$_12.JPG?set_id=880000500F","https://i.ebayimg.com/00/s/MTAwMVgxMDAx/z/I~4AAOSwz7FfYzN7/$_12.JPG?set_id=880000500F","https://i.ebayimg.com/00/s/MTAwMVgxMDAx/z/~50AAOSwAadfYzN8/$_12.JPG?set_id=880000500F","https://i.ebayimg.com/00/s/MTAwMVgxMDAx/z/JS8AAOSwGEZfYzN~/$_12.JPG?set_id=880000500F","https://i.ebayimg.com/00/s/MTAwMVgxMDAx/z/WbgAAOSwUTJfYzOB/$_12.JPG?set_id=880000500F","https://i.ebayimg.com/00/s/MTAwMVgxMDAx/z/X84AAOSwh7lfYzOC/$_12.JPG?set_id=880000500F","https://i.ebayimg.com/00/s/MTAwMVgxMDAx/z/zA4AAOSwUJNfYzOF/$_12.JPG?set_id=880000500F","https://i.ebayimg.com/00/s/MTAwMVgxMDAx/z/7EoAAOSwrmBfYzOH/$_12.JPG?set_id=880000500F"],"PrimaryCategoryID":"15280","PrimaryCategoryName":"Sporting Goods:Fitness, Running & Yoga:Cardio Equipment:Treadmills","BidCount":0,"ConvertedCurrentPrice":{"Value":259.99,"CurrencyID":"USD"},"ListingStatus":"Active","TimeLeft":"P19DT21H2M15S","Title":"Folding Electric Power Treadmill Motorized Walking Fitness Machine Running Home","HitCount":54986,"Country":"US","AutoPay":false,"ConditionID":1000,"ConditionDisplayName":"New","QuantityAvailableHint":"MoreThan","QuantityThreshold":10}]}