{"Timestamp":"2020-12-19T15:44:02.589Z","Ack":"Success","Build":"E1157_CORE_APILW_19146596_R1","Version":"1157","Item":[{"ItemID":"333217269175","EndTime":"2020-12-31T14:37:38.000Z","ViewItemURLForNaturalSearch":"https://www.ebay.com/itm/Canon-EOS-2000D-Rebel-T7-SLR-Camera-3-Lens-Kit-18-55mm-16GB-Flash-More-/333217269175","ListingType":"FixedPriceItem","Location":"Brooklyn, New York","GalleryURL":"https://thumbs4.ebaystatic.com/pict/3332172691758080_3.jpg","PictureURL":["https://i.ebayimg.com/00/s/NTAwWDUwMA==/z/hqUAAOSw7RteVBSB/$_1.JPG?set_id=8800005007","https://i.ebayimg.com/00/s/NTAwWDUwMA==/z/ZAkAAOSwIAVeVBSC/$_1.JPG?set_id=8800005007","https://i.ebayimg.com/00/s/NTAwWDUwMA==/z/50wAAOSwlyBeVBSD/$_1.JPG?set_id=8800005007","https://i.ebayimg.com/00/s/NTAwWDUwMA==/z/~WoAAOSwljFeVBSD/$_1.JPG?set_id=8800005007","https://i.ebayimg.com/00/s/NTAwWDUwMA==/z/SFgAAOSw8V9eVBSE/$_1.JPG?set_id=8800005007","https://i.ebayimg.com/00/s/NTAwWDUwMA==/z/iNsAAOSwPqZeVBSF/$_1.JPG?set_id=8800005007","https://i.ebayimg.com/00/s/NTAwWDUwMA==/z/onYAAOSweP9eVBSF/$_1.JPG?set_id=8800005007","https://i.ebayimg.com/00/s/NTAwWDUwMA==/z/PDYAAOSwHv1eVBSG/$_1.JPG?set_id=8800005007"],"PrimaryCategoryID":"31388","PrimaryCategoryName":"Cameras & Photo:Digital Cameras","BidCount":0,"ConvertedCurrentPrice":{"Value":529.95,"CurrencyID":"USD"},"ListingStatus":"Active","TimeLeft":"P11DT22H53M37S","Title":"Canon EOS 2000D / Rebel T7 SLR Camera + 3 Lens Kit 18-55mm + 16GB + Flash & More","HitCount":503305,"Country":"US","AutoPay":true,"ConditionID":1000,"ConditionDisplayName":"New","DiscountPriceInfo":{"OriginalRetailPrice":{"Value":579.95,"CurrencyID":"USD"},"PricingTreatment":"STP","SoldOneBay":false,"SoldOffeBay":false}},{"ItemID":"123920759504","EndTime":"2020-12-27T17:04:59.000Z","ViewItemURLForNaturalSearch":"https://www.ebay.com/itm/Sony-DSC-H300-BM-20-1MP-High-Zoom-Point-and-Shoot-Camera-35x-Zoom-Black-/123920759504","ListingType":"FixedPriceItem","Location":"Rogers, Arkansas","GalleryURL":"https://thumbs1.ebaystatic.com/pict/1239207595048080_2.jpg","PictureURL":["https://i.ebayimg.com/00/s/NjQ4WDc3Nw==/z/gVgAAOSw781djkFU/$_1.JPG?set_id=880000500F"],"PrimaryCategoryID":"31388","PrimaryCategoryName":"Cameras & Photo:Digital Cameras","BidCount":0,"ConvertedCurrentPrice":{"Value":99,"CurrencyID":"USD"},"ListingStatus":"Active","TimeLeft":"P8DT1H20M58S","Title":"Sony DSC-H300/BM 20.1MP High Zoom Point and Shoot Camera 35x Zoom Black","HitCount":90957,"Country":"US","AutoPay":true,"ConditionID":2500,"ConditionDisplayName":"Seller refurbished","DiscountPriceInfo":{"OriginalRetailPrice":{"Value":309,"CurrencyID":"USD"},"PricingTreatment":"STP","SoldOneBay":false,"SoldOffeBay":false}},{"ItemID":"323676266827","EndTime":"2021-01-01T16:53:47.000Z","ViewItemURLForNaturalSearch":"https://www.ebay.com/itm/Canon-EOS-M50-Camera-Body-Black-3-Lens-Kit-15-45mm-STM-32GB-Flash-More-/323676266827","ListingType":"FixedPriceItem","Location":"Brooklyn, New York","GalleryURL":"https://thumbs4.ebaystatic.com/pict/3236762668278080_2.jpg","PictureURL":["https://i.ebayimg.com/00/s/NTAwWDUwMA==/z/0MAAAOSwZGld0v8f/$_1.JPG?set_id=8800005007","https://i.ebayimg.com/00/s/NTAwWDUwMA==/z/KfoAAOSwh4td0v8h/$_1.JPG?set_id=8800005007","https://i.ebayimg.com/00/s/NTAwWDUwMA==/z/E6YAAOSwxjxd0v8h/$_1.JPG?set_id=8800005007","https://i.ebayimg.com/00/s/NTAwWDUwMA==/z/T5AAAOSwwRRd0v8i/$_1.JPG?set_id=8800005007","https://i.ebayimg.com/00/s/NTAwWDUwMA==/z/j1oAAOSwSRtd0v8j/$_1.JPG?set_id=8800005007","https://i.ebayimg.com/00/s/NTAwWDUwMA==/z/SAUAAOSwvqhd0v8j/$_1.JPG?set_id=8800005007","https://i.ebayimg.com/00/s/NTAwWDUwMA==/z/gEsAAOSwEhld0v8k/$_1.JPG?set_id=8800005007","https://i.ebayimg.com/00/s/NTAwWDUwMA==/z/qBIAAOSw-mtd0v8l/$_1.JPG?set_id=8800005007","https://i.ebayimg.com/00/s/NTAwWDUwMA==/z/4l0AAOSwL4Vd0v8l/$_1.JPG?set_id=8800005007"],"PrimaryCategoryID":"31388","PrimaryCategoryName":"Cameras & Photo:Digital Cameras","BidCount":0,"ConvertedCurrentPrice":{"Value":699.95,"CurrencyID":"USD"},"ListingStatus":"Active","TimeLeft":"P13DT1H9M46S","Title":"Canon EOS M50 Camera Body Black + 3 Lens Kit 15-45mm IS STM+ 32GB + Flash & More","HitCount":239348,"Country":"US","AutoPay":true,"ConditionID":1000,"ConditionDisplayName":"New","QuantityAvailableHint":"Limited"},{"ItemID":"333237405076","EndTime":"2021-01-17T21:21:24.000Z","ViewItemURLForNaturalSearch":"https://www.ebay.com/itm/Canon-EOS-4000D-Rebel-T100-SLR-Camera-3-Lens-Kit-18-55mm-16GB-Flash-More-/333237405076","ListingType":"FixedPriceItem","Location":"Brooklyn, New York","GalleryURL":"https://thumbs1.ebaystatic.com/pict/3332374050768080_1.jpg","PictureURL":["https://i.ebayimg.com/00/s/NTAwWDUwMA==/z/geIAAOSw5ZRdCARN/$_1.JPG?set_id=8800005007","https://i.ebayimg.com/00/s/NTAwWDUwMA==/z/VUUAAOSwG65dCARO/$_1.JPG?set_id=8800005007","https://i.ebayimg.com/00/s/NTAwWDUwMA==/z/xiQAAOSw5GNdCARP/$_1.JPG?set_id=8800005007","https://i.ebayimg.com/00/s/NTAwWDUwMA==/z/~ogAAOSwph1dCARP/$_1.JPG?set_id=8800005007","https://i.ebayimg.com/00/s/NTAwWDUwMA==/z/bPMAAOSwBlBdCARQ/$_1.JPG?set_id=8800005007","https://i.ebayimg.com/00/s/NTAwWDUwMA==/z/gzgAAOSwzixdCARR/$_1.JPG?set_id=8800005007","https://i.ebayimg.com/00/s/NTAwWDUwMA==/z/FY0AAOSw98RdCARR/$_1.JPG?set_id=8800005007","https://i.ebayimg.com/00/s/NTAwWDUwMA==/z/dDIAAOSwKEtdCARS/$_1.JPG?set_id=8800005007"],"PrimaryCategoryID":"31388","PrimaryCategoryName":"Cameras & Photo:Digital Cameras","BidCount":0,"ConvertedCurrentPrice":{"Value":469.95,"CurrencyID":"USD"},"ListingStatus":"Active","TimeLeft":"P29DT5H37M23S","Title":"Canon EOS 4000D / Rebel T100 SLR Camera + 3 Lens Kit 18-55mm+ 16GB+ Flash & More","HitCount":108791,"Country":"US","AutoPay":true,"ConditionID":1000,"ConditionDisplayName":"New"},{"ItemID":"184227162067","EndTime":"2020-12-26T16:44:29.000Z","ViewItemURLForNaturalSearch":"https://www.ebay.com/itm/Canon-EOS-2000D-Rebel-T7-24-1MP-DSLR-Camera-18-55mm-Lens-All-You-Need-Kit-/184227162067","ListingType":"FixedPriceItem","Location":"Fort Lauderdale, Florida","GalleryURL":"https://thumbs4.ebaystatic.com/pict/1842271620678080_1.jpg","PictureURL":["https://i.ebayimg.com/00/s/MTAwMFgxMDAw/z/~CoAAOSwLu5efNH8/$_57.JPG?set_id=8800005007","https://i.ebayimg.com/00/s/ODAwWDgwMA==/z/OKwAAOSw1r1efNPT/$_57.JPG?set_id=8800005007","https://i.ebayimg.com/00/s/ODAwWDgwMA==/z/HOUAAOSwaLxefNPU/$_57.JPG?set_id=8800005007","https://i.ebayimg.com/00/s/NTAwWDUwMA==/z/Zq4AAOSwhplefNPU/$_57.JPG?set_id=8800005007","https://i.ebayimg.com/00/s/NTAwWDUwMA==/z/C8gAAOSw0NZefNQF/$_57.JPG?set_id=8800005007","https://i.ebayimg.com/00/s/MTYwMFgxNTUz/z/y00AAOSwjmhefNt3/$_57.JPG?set_id=8800005007","https://i.ebayimg.com/00/s/MTEzMlgxNjAw/z/w3UAAOSwQahefNt6/$_57.JPG?set_id=8800005007","https://i.ebayimg.com/00/s/NTAwWDUwMA==/z/VHoAAOSwIYdefNt7/$_57.JPG?set_id=8800005007","https://i.ebayimg.com/00/s/NTAwWDUwMA==/z/YgkAAOSwugJefNt7/$_57.JPG?set_id=8800005007","https://i.ebayimg.com/00/s/OTQ2WDgxNg==/z/yaAAAOSwVWFefNud/$_57.JPG?set_id=8800005007","https://i.ebayimg.com/00/s/NDQyWDEwMDA=/z/vJgAAOSwiiZefNva/$_57.JPG?set_id=8800005007","https://i.ebayimg.com/00/s/MTAwMFgxMDAw/z/7V0AAOSwnTBefNvf/$_57.JPG?set_id=8800005007"],"PrimaryCategoryID":"31388","PrimaryCategoryName":"Cameras & Photo:Digital Cameras","BidCount":0,"ConvertedCurrentPrice":{"Value":499.97,"CurrencyID":"USD"},"ListingStatus":"Active","TimeLeft":"P7DT1H27S","Title":"Canon EOS 2000D / Rebel T7 24.1MP DSLR Camera + 18-55mm Lens + All You Need Kit","HitCount":214896,"Country":"US","AutoPay":true,"ConditionID":1000,"ConditionDisplayName":"New","QuantityAvailableHint":"MoreThan","QuantityThreshold":10},{"ItemID":"372854059449","EndTime":"2020-12-25T17:45:16.000Z","ViewItemURLForNaturalSearch":"https://www.ebay.com/itm/Panasonic-LUMIX-FZ80-4K-60X-20-1200mm-Zoom-Bird-Wildlife-Camera-WiFi-USA-Version-/372854059449","ListingType":"FixedPriceItem","Location":"Brooklyn, New York","GalleryURL":"https://thumbs2.ebaystatic.com/pict/3728540594498080_2.jpg","PictureURL":["https://i.ebayimg.com/00/s/MTA2NlgxNTk5/z/7XYAAOSwXk1d5pwB/$_57.JPG?set_id=8800005007","https://i.ebayimg.com/00/s/MTA2NlgxNTk5/z/~rEAAOSwNcRd5pwG/$_57.JPG?set_id=8800005007","https://i.ebayimg.com/00/s/MTA2NlgxNTk5/z/n24AAOSwVYNd5pwI/$_57.JPG?set_id=8800005007","https://i.ebayimg.com/00/s/MTA2NlgxNTk5/z/4cQAAOSwuEhd5pwK/$_57.JPG?set_id=8800005007","https://i.ebayimg.com/00/s/MTUwMFgxNTAw/z/LGoAAOSw8A1d3BKs/$_57.JPG?set_id=8800005007","https://i.ebayimg.com/00/s/NDQ3WDUwMA==/z/3BIAAOSw7xZd3BKi/$_57.JPG?set_id=8800005007","https://i.ebayimg.com/00/s/MTUwMFgxNTAw/z/eIcAAOSwHX9d3BKo/$_57.JPG?set_id=8800005007","https://i.ebayimg.com/00/s/MTUwMFgxNTAw/z/1akAAOSwOFZd3BKq/$_57.JPG?set_id=8800005007","https://i.ebayimg.com/00/s/MTUwMFgxNTAw/z/~mIAAOSw8hpd3BKm/$_57.JPG?set_id=8800005007","https://i.ebayimg.com/00/s/NTAwWDUwMA==/z/rJ8AAOSwW1Bd3BKr/$_57.JPG?set_id=8800005007","https://i.ebayimg.com/00/s/NTAwWDUwMA==/z/WtgAAOSww5Zd3BKj/$_57.JPG?set_id=8800005007","https://i.ebayimg.com/00/s/NTAwWDUwMA==/z/u4oAAOSwUCFd3BKj/$_57.JPG?set_id=8800005007"],"PrimaryCategoryID":"31388","PrimaryCategoryName":"Cameras & Photo:Digital Cameras","BidCount":0,"ConvertedCurrentPrice":{"Value":279.99,"CurrencyID":"USD"},"ListingStatus":"Active","TimeLeft":"P6DT2H1M14S","Title":"Panasonic LUMIX FZ80 4K 60X 20-1200mm Zoom Bird Wildlife Camera WiFi USA Version","HitCount":63581,"Country":"US","AutoPay":true,"ConditionID":1500,"ConditionDisplayName":"Open box","GlobalShipping":true,"ConditionDescription":"USA manufacturer direct warranty. Open box item in original manufacturer box. Paper manual may be missing."},{"ItemID":"223183887864","EndTime":"2021-01-10T14:42:48.000Z","ViewItemURLForNaturalSearch":"https://www.ebay.com/itm/Nikon-D3500-Digital-SLR-Camera-Black-3-Lens-18-55mm-VR-Lens-32GB-Bundle-/223183887864","ListingType":"FixedPriceItem","Location":"Brooklyn, New York","GalleryURL":"https://thumbs1.ebaystatic.com/pict/2231838878648080_4.jpg","PictureURL":["https://i.ebayimg.com/00/s/NTAwWDUwMA==/z/kNwAAOSwRfNeOE41/$_1.JPG?set_id=8800005007","https://i.ebayimg.com/00/s/NTAwWDUwMA==/z/r14AAOSwTJJeOE42/$_1.JPG?set_id=8800005007","https://i.ebayimg.com/00/s/NTAwWDUwMA==/z/tAQAAOSwvgheOE43/$_1.JPG?set_id=8800005007","https://i.ebayimg.com/00/s/NTAwWDUwMA==/z/ILsAAOSwYABeOE44/$_1.JPG?set_id=8800005007","https://i.ebayimg.com/00/s/NTAwWDUwMA==/z/gTsAAOSw46BeOE44/$_1.JPG?set_id=8800005007","https://i.ebayimg.com/00/s/NTAwWDUwMA==/z/X80AAOSwUEheOE45/$_1.JPG?set_id=8800005007","https://i.ebayimg.com/00/s/NTAwWDUwMA==/z/j8AAAOSw1UpeOE46/$_1.JPG?set_id=8800005007","https://i.ebayimg.com/00/s/NTAwWDUwMA==/z/PnUAAOSwYBpeOE46/$_1.JPG?set_id=8800005007"],"PrimaryCategoryID":"31388","PrimaryCategoryName":"Cameras & Photo:Digital Cameras","BidCount":0,"ConvertedCurrentPrice":{"Value":669.95,"CurrencyID":"USD"},"ListingStatus":"Active","TimeLeft":"P21DT22H58M46S","Title":"Nikon D3500 Digital SLR Camera Black + 3 Lens: 18-55mm VR Lens + 32GB Bundle","HitCount":240031,"Country":"US","AutoPay":true,"ConditionID":1000,"ConditionDisplayName":"New"},{"ItemID":"164281403678","EndTime":"2021-01-08T06:44:32.000Z","ViewItemURLForNaturalSearch":"https://www.ebay.com/itm/Digital-SLR-Camera-3-0-Inch-TFT-LCD-Screen-16X-Zoom-HD-16MP-1080P-Anti-shake-/164281403678","ListingType":"FixedPriceItem","Location":"New Jersey","GalleryURL":"https://thumbs3.ebaystatic.com/pict/1642814036788080_1.jpg","PictureURL":["https://i.ebayimg.com/00/s/MTQyNVgxNTAw/z/8-sAAOSw5kdesQfs/$_57.JPG?set_id=8800005007","https://i.ebayimg.com/00/s/ODAwWDgwMA==/z/c8oAAOSwUi5esQg6/$_57.JPG?set_id=8800005007","https://i.ebayimg.com/00/s/ODAwWDgwMA==/z/DEkAAOSw0jtesQg9/$_57.JPG?set_id=8800005007","https://i.ebayimg.com/00/s/ODAwWDgwMA==/z/oMYAAOSwkBtesQhB/$_57.JPG?set_id=8800005007","https://i.ebayimg.com/00/s/OTE0WDk0MA==/z/VPoAAOSw6TxesQfw/$_57.JPG?set_id=8800005007","https://i.ebayimg.com/00/s/NzcyWDY5MQ==/z/VU4AAOSwOfFesQfz/$_57.JPG?set_id=8800005007","https://i.ebayimg.com/00/s/ODg1WDc4MA==/z/6OoAAOSw6wdesQf2/$_57.JPG?set_id=8800005007","https://i.ebayimg.com/00/s/ODkzWDczMg==/z/4ZEAAOSwqptesQf6/$_57.JPG?set_id=8800005007","https://i.ebayimg.com/00/s/NzY0WDc0Nw==/z/KtcAAOSwxZtesQf8/$_57.JPG?set_id=8800005007","https://i.ebayimg.com/00/s/NDY2WDY3OQ==/z/nFYAAOSwOmBesQgB/$_57.JPG?set_id=8800005007","https://i.ebayimg.com/00/s/NzUwWDk5Ng==/z/c4YAAOSwUi5esQgG/$_57.JPG?set_id=8800005007","https://i.ebayimg.com/00/s/NzkwWDU3OA==/z/Bv8AAOSwHk9esQgN/$_57.JPG?set_id=8800005007"],"PrimaryCategoryID":"31388","PrimaryCategoryName":"Cameras & Photo:Digital Cameras","BidCount":0,"ConvertedCurrentPrice":{"Value":38.99,"CurrencyID":"USD"},"ListingStatus":"Active","TimeLeft":"P19DT15H30S","Title":"Digital SLR Camera 3.0 Inch TFT LCD Screen 16X Zoom HD 16MP 1080P  Anti-shake","HitCount":49600,"Country":"US","AutoPay":true,"ConditionID":1000,"ConditionDisplayName":"New","QuantityAvailableHint":"MoreThan","QuantityThreshold":10},{"ItemID":"322843979832","EndTime":"2020-12-23T17:39:54.000Z","ViewItemURLForNaturalSearch":"https://www.ebay.com/itm/Canon-IXUS-185-ELPH-180-20-0MP-Digital-Camera-8x-Optical-Zoom-Black-16GB-Kit-/322843979832","ListingType":"FixedPriceItem","Location":"Brooklyn, New York","GalleryURL":"https://thumbs1.ebaystatic.com/pict/3228439798328080_2.jpg","PictureURL":["https://i.ebayimg.com/00/s/NTAwWDUwMA==/z/nWQAAOSwT2daMbLB/$_1.JPG?set_id=8800005007","https://i.ebayimg.com/00/s/NTAwWDUwMA==/z/7JMAAOSwNchaMbLD/$_1.JPG?set_id=8800005007","https://i.ebayimg.com/00/s/NTAwWDUwMA==/z/P6gAAOSwg8taMbLE/$_1.JPG?set_id=8800005007","https://i.ebayimg.com/00/s/NTAwWDUwMA==/z/7ykAAOSwCtJaMbLE/$_1.JPG?set_id=8800005007","https://i.ebayimg.com/00/s/NTAwWDUwMA==/z/8XAAAOSwzRlaMbLF/$_1.JPG?set_id=8800005007"],"PrimaryCategoryID":"31388","PrimaryCategoryName":"Cameras & Photo:Digital Cameras","BidCount":0,"ConvertedCurrentPrice":{"Value":129.95,"CurrencyID":"USD"},"ListingStatus":"Active","TimeLeft":"P4DT1H55M53S","Title":"Canon IXUS 185 / ELPH 180 20.0MP Digital Camera 8x Optical Zoom Black + 16GB Kit","HitCount":13261,"Country":"US","AutoPay":true,"ConditionID":1000,"ConditionDisplayName":"New"},{"ItemID":"202653824208","EndTime":"2021-01-14T19:11:18.000Z","ViewItemURLForNaturalSearch":"https://www.ebay.com/itm/Canon-EOS-Rebel-T7i-DSLR-Camera-EF-S-18-55mm-STM-Lens-Black-/202653824208","ListingType":"FixedPriceItem","Location":"Brooklyn, New York","GalleryURL":"https://thumbs1.ebaystatic.com/pict/2026538242088080_2.jpg","PictureURL":["https://i.ebayimg.com/00/s/MTYwMFgxNjAw/z/XNQAAOSwM8NcvydL/$_57.JPG?set_id=8800005007","https://i.ebayimg.com/00/s/MTYwMFgxNjAw/z/ll0AAOSwFGJcvydP/$_57.JPG?set_id=8800005007"],"PrimaryCategoryID":"31388","PrimaryCategoryName":"Cameras & Photo:Digital Cameras","BidCount":0,"ConvertedCurrentPrice":{"Value":512.99,"CurrencyID":"USD"},"ListingStatus":"Active","TimeLeft":"P26DT3H27M16S","Title":"Canon EOS Rebel T7i DSLR Camera with EF-S 18-55mm IS STM Lens Black","HitCount":32963,"Country":"US","AutoPay":true,"ConditionID":2500,"ConditionDisplayName":"Seller refurbished","QuantityAvailableHint":"MoreThan","QuantityThreshold":10,"ConditionDescription":"Fully tested and working, will have scratches/scuffs/etc."},{"ItemID":"402615280692","BuyItNowAvailable":true,"ConvertedBuyItNowPrice":{"Value":150,"CurrencyID":"USD"},"EndTime":"2020-12-26T06:03:10.000Z","ViewItemURLForNaturalSearch":"https://www.ebay.com/itm/Ricoh-GR-Digital-II-10-1-MP-Excellent-Condition-/402615280692","ListingType":"Chinese","Location":"Los Angeles, California","GalleryURL":"https://thumbs1.ebaystatic.com/pict/4026152806928080_1.jpg","PictureURL":["https://i.ebayimg.com/00/s/MTYwMFgxMjAw/z/EyUAAOSwcmVf3ZXv/$_12.JPG?set_id=880000500F","https://i.ebayimg.com/00/s/MTYwMFgxMjAw/z/pKMAAOSwkUJf3ZXF/$_12.JPG?set_id=880000500F","https://i.ebayimg.com/00/s/MTYwMFgxMjAw/z/0mYAAOSwLDtf3ZXH/$_12.JPG?set_id=880000500F"],"PrimaryCategoryID":"31388","PrimaryCategoryName":"Cameras & Photo:Digital Cameras","BidCount":0,"ConvertedCurrentPrice":{"Value":100,"CurrencyID":"USD"},"ListingStatus":"Active","TimeLeft":"P6DT14H19M8S","Title":"Ricoh GR Digital II 10.1 MP Excellent Condition","HitCount":38,"Country":"US","AutoPay":false,"ConditionID":2500,"ConditionDisplayName":"Seller refurbished"},{"ItemID":"174266024003","EndTime":"2020-12-29T17:48:10.000Z","ViewItemURLForNaturalSearch":"https://www.ebay.com/itm/Canon-EOS-R-Mirrorless-Digital-Camera-Body-3075C002-/174266024003","ListingType":"FixedPriceItem","Location":"Ontario","GalleryURL":"https://thumbs4.ebaystatic.com/pict/1742660240038080_1.jpg","PictureURL":["https://i.ebayimg.com/00/s/NTAwWDUwMA==/z/SFUAAOSwkBteqb3d/$_1.JPG?set_id=8800005007","https://i.ebayimg.com/00/s/NTAwWDUwMA==/z/F2QAAOSwnfVeqb3d/$_1.JPG?set_id=8800005007","https://i.ebayimg.com/00/s/NTAwWDUwMA==/z/XnEAAOSw0UNeqb3d/$_1.JPG?set_id=8800005007","https://i.ebayimg.com/00/s/NTAwWDUwMA==/z/RxYAAOSwHZBeqb3d/$_1.JPG?set_id=8800005007"],"PrimaryCategoryID":"31388","PrimaryCategoryName":"Cameras & Photo:Digital Cameras","BidCount":0,"ConvertedCurrentPrice":{"Value":1489.99,"CurrencyID":"USD"},"ListingStatus":"Active","TimeLeft":"P10DT2H4M8S","Title":"Canon EOS R Mirrorless Digital Camera Body 3075C002","HitCount":47933,"Country":"CA","AutoPay":true,"ConditionID":1000,"ConditionDisplayName":"New","QuantityAvailableHint":"Limited","DiscountPriceInfo":{"OriginalRetailPrice":{"Value":1799.99,"CurrencyID":"USD"},"PricingTreatment":"STP","SoldOneBay":false,"SoldOffeBay":false}},{"ItemID":"322857453639","EndTime":"2020-12-31T19:55:36.000Z","ViewItemURLForNaturalSearch":"https://www.ebay.com/itm/Nikon-D850-DSLR-Camera-Body-Only-/322857453639","ListingType":"FixedPriceItem","Location":"Somerset, New Jersey","GalleryURL":"https://thumbs4.ebaystatic.com/pict/3228574536398080_4.jpg","PictureURL":["https://i.ebayimg.com/00/s/NTAwWDUwMA==/z/hHkAAOSwT~hdP4~H/$_1.JPG?set_id=8800005007","https://i.ebayimg.com/00/s/NTk1WDcwMA==/z/NyoAAOSw3VpftAqe/$_12.PNG?set_id=880000500F","https://i.ebayimg.com/00/s/NTk1WDcwMA==/z/0bQAAOSwQJlftAqe/$_12.PNG?set_id=880000500F","https://i.ebayimg.com/00/s/NTk1WDcwMA==/z/IoMAAOSw8XRftAqe/$_12.PNG?set_id=880000500F","https://i.ebayimg.com/00/s/NTk1WDcwMA==/z/SQIAAOSwcLRftAqe/$_12.PNG?set_id=880000500F"],"PrimaryCategoryID":"31388","PrimaryCategoryName":"Cameras & Photo:Digital Cameras","BidCount":0,"ConvertedCurrentPrice":{"Value":2579.95,"CurrencyID":"USD"},"ListingStatus":"Active","TimeLeft":"P12DT4H11M35S","Title":"Nikon D850 DSLR Camera (Body Only)","HitCount":500510,"Country":"US","AutoPay":true,"ConditionID":1000,"ConditionDisplayName":"New","QuantityAvailableHint":"MoreThan","QuantityThreshold":10,"DiscountPriceInfo":{"OriginalRetailPrice":{"Value":2996.95,"CurrencyID":"USD"},"PricingTreatment":"STP","SoldOneBay":false,"SoldOffeBay":false}},{"ItemID":"223536368241","EndTime":"2020-12-31T14:41:26.000Z","ViewItemURLForNaturalSearch":"https://www.ebay.com/itm/Canon-EOS-2000D-Rebel-T7-DSLR-Camera-18-55mm-Lens-30-Piece-Accessory-Bundle-/223536368241","ListingType":"FixedPriceItem","Location":"Brooklyn, New York","GalleryURL":"https://thumbs2.ebaystatic.com/pict/2235363682418080_1.jpg","PictureURL":["https://i.ebayimg.com/00/s/NTAwWDUwMA==/z/hOYAAOSwIJ1c8T0O/$_1.JPG?set_id=8800005007","https://i.ebayimg.com/00/s/NTAwWDUwMA==/z/locAAOSwYPNc8T0P/$_1.JPG?set_id=8800005007","https://i.ebayimg.com/00/s/NTAwWDUwMA==/z/0MgAAOSwsvxc8T0Q/$_1.JPG?set_id=8800005007","https://i.ebayimg.com/00/s/NTAwWDUwMA==/z/99wAAOSwVaZc8T0R/$_1.JPG?set_id=8800005007","https://i.ebayimg.com/00/s/NTAwWDUwMA==/z/h74AAOSwYrFc8T0R/$_1.JPG?set_id=8800005007","https://i.ebayimg.com/00/s/NTAwWDUwMA==/z/75UAAOSwT~9c8T0S/$_1.JPG?set_id=8800005007","https://i.ebayimg.com/00/s/NTAwWDUwMA==/z/ETMAAOSwK6Jc8T0T/$_1.JPG?set_id=8800005007","https://i.ebayimg.com/00/s/NTAwWDUwMA==/z/baMAAOSw0ilc8T0T/$_1.JPG?set_id=8800005007"],"PrimaryCategoryID":"31388","PrimaryCategoryName":"Cameras & Photo:Digital Cameras","BidCount":0,"ConvertedCurrentPrice":{"Value":559.95,"CurrencyID":"USD"},"ListingStatus":"Active","TimeLeft":"P11DT22H57M24S","Title":"Canon EOS 2000D / Rebel T7 DSLR Camera + 18-55mm Lens+ 30 Piece Accessory Bundle","HitCount":71486,"Country":"US","AutoPay":true,"ConditionID":1000,"ConditionDisplayName":"New","DiscountPriceInfo":{"OriginalRetailPrice":{"Value":654.99,"CurrencyID":"USD"},"PricingTreatment":"STP","SoldOneBay":false,"SoldOffeBay":false}},{"ItemID":"352544912878","EndTime":"2021-01-14T19:24:00.000Z","ViewItemURLForNaturalSearch":"https://www.ebay.com/itm/Canon-PowerShot-SX430-Digital-SLR-Camera-Black-/352544912878","ListingType":"FixedPriceItem","Location":"Brooklyn, New York","GalleryURL":"https://thumbs3.ebaystatic.com/pict/3525449128788080_1.jpg","PictureURL":["https://i.ebayimg.com/00/s/ODYxWDExOTA=/z/MpoAAOSwliFcFANP/$_12.JPG?set_id=880000500F"],"PrimaryCategoryID":"31388","PrimaryCategoryName":"Cameras & Photo:Digital Cameras","BidCount":0,"ConvertedCurrentPrice":{"Value":185.97,"CurrencyID":"USD"},"ListingStatus":"Active","TimeLeft":"P26DT3H39M58S","Title":"Canon PowerShot SX430 IS Digital SLR Camera (Black)","HitCount":7874,"Country":"US","AutoPay":true,"ConditionID":1000,"ConditionDisplayName":"New","QuantityAvailableHint":"MoreThan","QuantityThreshold":10,"DiscountPriceInfo":{"OriginalRetailPrice":{"Value":187.97,"CurrencyID":"USD"},"PricingTreatment":"STP","SoldOneBay":false,"SoldOffeBay":false},"GlobalShipping":true},{"ItemID":"223555593567","EndTime":"2021-01-17T21:31:02.000Z","ViewItemURLForNaturalSearch":"https://www.ebay.com/itm/Canon-EOS-4000D-T100-SLR-Camera-w-18-55mm-16GB-3-Lens-Ultimate-Accessory-Kit-/223555593567","ListingType":"FixedPriceItem","Location":"Brooklyn, New York","GalleryURL":"https://thumbs4.ebaystatic.com/pict/2235555935678080_1.jpg","PictureURL":["https://i.ebayimg.com/00/s/NTAwWDUwMA==/z/VkIAAOSwYdpdCAaN/$_1.JPG?set_id=8800005007","https://i.ebayimg.com/00/s/NTAwWDUwMA==/z/JwoAAOSwzbtdCAaQ/$_1.JPG?set_id=8800005007","https://i.ebayimg.com/00/s/NTAwWDUwMA==/z/gFoAAOSwz~RdCAaR/$_1.JPG?set_id=8800005007","https://i.ebayimg.com/00/s/NTAwWDUwMA==/z/fmIAAOSw2EZdCAaR/$_1.JPG?set_id=8800005007","https://i.ebayimg.com/00/s/NTAwWDUwMA==/z/IDAAAOSwA3ldCAaS/$_1.JPG?set_id=8800005007","https://i.ebayimg.com/00/s/NTAwWDUwMA==/z/xwUAAOSw0wldCAaT/$_1.JPG?set_id=8800005007","https://i.ebayimg.com/00/s/NTAwWDUwMA==/z/H6kAAOSw~hNdCAaT/$_1.JPG?set_id=8800005007","https://i.ebayimg.com/00/s/NTAwWDUwMA==/z/V~0AAOSwRWtdCAaU/$_1.JPG?set_id=8800005007"],"PrimaryCategoryID":"31388","PrimaryCategoryName":"Cameras & Photo:Digital Cameras","BidCount":0,"ConvertedCurrentPrice":{"Value":479.95,"CurrencyID":"USD"},"ListingStatus":"Active","TimeLeft":"P29DT5H47M","Title":"Canon EOS 4000D / T100 SLR Camera w/ 18-55mm+ 16GB 3 Lens Ultimate Accessory Kit","HitCount":20139,"Country":"US","AutoPay":true,"ConditionID":1000,"ConditionDisplayName":"New"},{"ItemID":"224284903241","EndTime":"2021-01-19T04:23:44.000Z","ViewItemURLForNaturalSearch":"https://www.ebay.com/itm/Fujifilm-GFX-50R-51-4MP-Digital-Camera-Black-Body-Only-/224284903241","ListingType":"FixedPriceItem","Location":"Idyllwild, California","GalleryURL":"https://thumbs2.ebaystatic.com/pict/2242849032418080_1.jpg","PictureURL":["https://i.ebayimg.com/00/s/MTYwMFgxMjAw/z/~XMAAOSw21pf3X7i/$_57.JPG?set_id=8800005007","https://i.ebayimg.com/00/s/MTIwMFgxNjAw/z/eGcAAOSwK8Nf3X7s/$_57.JPG?set_id=8800005007","https://i.ebayimg.com/00/s/MTIwMFgxNjAw/z/cl8AAOSw~tpf3X7z/$_57.JPG?set_id=8800005007","https://i.ebayimg.com/00/s/MTIwMFgxNjAw/z/Jp8AAOSwnF1f3X78/$_57.JPG?set_id=8800005007","https://i.ebayimg.com/00/s/MTIwMFgxNjAw/z/ahMAAOSwzlxf3X8d/$_57.JPG?set_id=8800005007"],"PrimaryCategoryID":"31388","PrimaryCategoryName":"Cameras & Photo:Digital Cameras","BidCount":0,"ConvertedCurrentPrice":{"Value":3349,"CurrencyID":"USD"},"ListingStatus":"Active","TimeLeft":"P30DT12H39M42S","Title":"Fujifilm GFX 50R 51.4MP Digital Camera - Black (Body Only)","HitCount":99,"Country":"US","AutoPay":false,"ConditionID":3000,"ConditionDisplayName":"Used","ConditionDescription":"Like New barely used"},{"ItemID":"323822097136","EndTime":"2020-12-31T14:42:41.000Z","ViewItemURLForNaturalSearch":"https://www.ebay.com/itm/Canon-EOS-2000D-Rebel-T7-DSLR-Camera-18-55mm-70-300mm-30-Piece-Bundle-/323822097136","ListingType":"FixedPriceItem","Location":"Brooklyn, New York","GalleryURL":"https://thumbs1.ebaystatic.com/pict/3238220971368080_1.jpg","PictureURL":["https://i.ebayimg.com/00/s/NTAwWDUwMA==/z/3loAAOSwZRZc8T1Z/$_1.JPG?set_id=8800005007","https://i.ebayimg.com/00/s/NTAwWDUwMA==/z/HDEAAOSwD8Bc8T1Z/$_1.JPG?set_id=8800005007","https://i.ebayimg.com/00/s/NTAwWDUwMA==/z/DTAAAOSwU55c8T1a/$_1.JPG?set_id=8800005007","https://i.ebayimg.com/00/s/NTAwWDUwMA==/z/lewAAOSwXGVc8T1b/$_1.JPG?set_id=8800005007","https://i.ebayimg.com/00/s/NTAwWDUwMA==/z/9C0AAOSwoltc8T1b/$_1.JPG?set_id=8800005007","https://i.ebayimg.com/00/s/NTAwWDUwMA==/z/XoEAAOSwQ8Rc8T1c/$_1.JPG?set_id=8800005007","https://i.ebayimg.com/00/s/NTAwWDUwMA==/z/NsgAAOSwedRc8T1d/$_1.JPG?set_id=8800005007","https://i.ebayimg.com/00/s/NTAwWDUwMA==/z/iaoAAOSwhf9c8T1d/$_1.JPG?set_id=8800005007"],"PrimaryCategoryID":"31388","PrimaryCategoryName":"Cameras & Photo:Digital Cameras","BidCount":0,"ConvertedCurrentPrice":{"Value":699.95,"CurrencyID":"USD"},"ListingStatus":"Active","TimeLeft":"P11DT22H58M40S","Title":"Canon EOS 2000D / Rebel T7 DSLR Camera + 18-55mm + 70-300mm + 30 Piece Bundle","HitCount":78563,"Country":"US","AutoPay":true,"ConditionID":1000,"ConditionDisplayName":"New","DiscountPriceInfo":{"OriginalRetailPrice":{"Value":849.99,"CurrencyID":"USD"},"PricingTreatment":"STP","SoldOneBay":false,"SoldOffeBay":false}},{"ItemID":"182598748472","EndTime":"2020-12-30T15:46:19.000Z","ViewItemURLForNaturalSearch":"https://www.ebay.com/itm/Panasonic-LUMIX-DC-FZ80-4K-60x-Zoom-Digital-Camera-Black-NEW-/182598748472","ListingType":"FixedPriceItem","Location":"Ontario","GalleryURL":"https://thumbs1.ebaystatic.com/pict/1825987484728080_5.jpg","PictureURL":["https://i.ebayimg.com/00/s/NTAwWDUwMA==/z/ptcAAOSwCQZZLZNe/$_57.JPG?set_id=8800005007","https://i.ebayimg.com/00/s/NTAwWDUwMA==/z/znwAAOSwurZZLZNc/$_57.JPG?set_id=8800005007","https://i.ebayimg.com/00/s/NTAwWDUwMA==/z/aMsAAOSw3gJZLZNa/$_57.JPG?set_id=8800005007","https://i.ebayimg.com/00/s/NTAwWDUwMA==/z/BvQAAOSwZKBZLZNd/$_57.JPG?set_id=8800005007"],"PrimaryCategoryID":"31388","PrimaryCategoryName":"Cameras & Photo:Digital Cameras","BidCount":0,"ConvertedCurrentPrice":{"Value":304.99,"CurrencyID":"USD"},"ListingStatus":"Active","TimeLeft":"P11DT2M17S","Title":"Panasonic LUMIX DC-FZ80 4K/60x Zoom Digital Camera - Black NEW!","HitCount":86308,"Country":"CA","AutoPay":true,"ConditionID":1000,"ConditionDisplayName":"New","QuantityAvailableHint":"Limited","DiscountPriceInfo":{"OriginalRetailPrice":{"Value":397.99,"CurrencyID":"USD"},"PricingTreatment":"STP","SoldOneBay":false,"SoldOffeBay":false}},{"ItemID":"322547567928","EndTime":"2021-01-08T14:18:32.000Z","ViewItemURLForNaturalSearch":"https://www.ebay.com/itm/Canon-PowerShot-SX620-HS-20-2MP-25X-Zoom-Wifi-Digital-Camera-32GB-Accessory-Kit-/322547567928","ListingType":"FixedPriceItem","Location":"Brooklyn, New York","GalleryURL":"https://thumbs1.ebaystatic.com/pict/3225475679288080_1.jpg","PictureURL":["https://i.ebayimg.com/00/s/MTAwMFgxMDAw/z/rGEAAOSw5UZZANaS/$_12.JPG?set_id=880000500F","https://i.ebayimg.com/00/s/MTAwMFgxMDAw/z/HKsAAOSwvihZANaK/$_12.JPG?set_id=880000500F","https://i.ebayimg.com/00/s/MTAwMFgxMDAw/z/6JQAAOSwVm5ZANaN/$_12.JPG?set_id=880000500F","https://i.ebayimg.com/00/s/MTAwMFgxMDAw/z/NvAAAOSwE0JZANaR/$_12.JPG?set_id=880000500F","https://i.ebayimg.com/00/s/MTAwMFgxMDAw/z/nBcAAOSwvbdZANaS/$_12.JPG?set_id=880000500F","https://i.ebayimg.com/00/s/MTAwMFgxMDAw/z/K-AAAOSwrrFZANaT/$_12.JPG?set_id=880000500F","https://i.ebayimg.com/00/s/MTAwMFgxMDAw/z/rO0AAOSw5UZZANaU/$_12.JPG?set_id=880000500F","https://i.ebayimg.com/00/s/MTAwMFgxMDAw/z/62MAAOSwIWVZANaV/$_12.JPG?set_id=880000500F"],"PrimaryCategoryID":"31388","PrimaryCategoryName":"Cameras & Photo:Digital Cameras","BidCount":0,"ConvertedCurrentPrice":{"Value":247.99,"CurrencyID":"USD"},"ListingStatus":"Active","TimeLeft":"P19DT22H34M31S","Title":"Canon PowerShot SX620 HS 20.2MP 25X Zoom Wifi Digital Camera 32GB Accessory Kit","HitCount":93793,"Country":"US","AutoPay":true,"ConditionID":1000,"ConditionDisplayName":"New","DiscountPriceInfo":{"OriginalRetailPrice":{"Value":279,"CurrencyID":"USD"},"PricingTreatment":"STP","SoldOneBay":false,"SoldOffeBay":false}}]}